{
"innhold": [
    {
      "type": "barchart",
      "data": "qwerty",
      "x": ["Snittrate"],
      "y": "bohf",
      "xLabel": {
        "nn": "Tal kontaktar hos allmennlege pr. 1 000 innbyggjarar (under 18 år)",
        "en": "Primary care contact per 1,000 population (under 18 years)"
      },
      "yLabel": {
        "nn": "Opptaksområde",
        "en": "Referral areas"
      },
      "annualVar": [
        "Rate.2019",
        "Rate.2020",
        "Rate.2021",
        "Rate.2022",
        "Rate.2023"
      ],
      "annualVarLabels": {
        "nn": [ "2019", "2020", "2021", "2022", "2023"],
        "en": [ "2019", "2020", "2021", "2022", "2023"]
      }
    },
    {
      "type": "table",
      "data": "qwerty",
      "caption": {
        "nn": "Årlege gjennomsnittsverdiar for perioden 2019–2023. Rate pr. 1 000 innbyggjarar under 18 år",
        "en": "Annual average during 2019–2023. Rate pr. 1 000 population under 18 years"
      },
      "columns": [
        {
          "id": "bohf",
          "label_no": "Opptaksområde",
          "label_en": "Referral areas",
          "typeVar": "string",
          "format": ""
        },
        {
          "id": "Snittrate",
          "label_no": "Kontaktrate",
          "label_en": "Contact rate",
          "typeVar": "number",
          "format": ",.1f"
        },
        {
          "id": "Snitt_kontaktar",
          "label_no": "Tal kontaktar hos allmennlege",
          "label_en": "Number of contacts",
          "typeVar": "number",
          "format": ",.0f"
        },
        {
          "id": "Snitt_innbyggarar",
          "label_no": "Inbyggjarar (under 18 år)",
          "label_en": "Population (under 18 years)",
          "typeVar": "number",
          "format": ",.0f"
        }
      ]
    },
  {
      "type": "table",
      "data": "qwerty",
      "caption": {
        "nn": "Årlege gjennomsnittsverdiar for perioden 2019–2023. Tal kontaktar per pasient",
        "en": "Annual average during 2019–2023. Number of contact per patient"
      },
      "columns": [
        {
          "id": "bohf",
          "label_no": "Opptaksområde",
          "label_en": "Referral areas",
          "typeVar": "string",
          "format": ""
        },
        {
          "id": "kontakt_p_pas",
          "label_no": "Kontaktar per pasient",
          "label_en": "Contacts per patient",
          "typeVar": "number",
          "format": ",.1f"
        },
        {
          "id": "Snitt_kontaktar",
          "label_no": "Tal kontaktar",
          "label_en": "Number of contacts",
          "typeVar": "number",
          "format": ",.0f"
        },
        {
          "id": "Tal_pas",
          "label_no": "Tal pasientar",
          "label_en": "Number of patients",
          "typeVar": "number",
          "format": ",.0f"
        }
      ]
    },
{
      "type": "map",
      "data": "qwerty",
      "x": "Snittrate",
      "caption": {
        "nn": "Tal kontaktar pr. 1 000 innbyggjarar (under 18 år )",
        "en": "Number of contacts  per 1,000 population (under 18 years)"
      },
      "jenks": [
        {
          "grense": 94.6
        },
        {
          "grense": 108.1
        },
        {
          "grense": 121.4
        }
      ]
    },
    {
      "type": "data",
      "label": "qwerty",
      "description": "Hoveddatasettet for gitt resultatboks",
      "national": "Noreg",
      "data":

[
  {
    "bohf": "Førde",
    "Snitt_kontaktar": 1988.6,
    "Snitt_innbyggarar": 23040.4,
    "Snittrate": 83.51,
    "Rate.2019": 68.06,
    "Rate.2020": 73.28,
    "Rate.2021": 90.4,
    "Rate.2022": 89.34,
    "Rate.2023": 96.47,
    "Tal_pas": 1129.6,
    "kontakt_p_pas": 1.7604
  },
  {
    "bohf": "Helgeland",
    "Snitt_kontaktar": 1393.8,
    "Snitt_innbyggarar": 15107.6,
    "Snittrate": 89.96,
    "Rate.2019": 79.48,
    "Rate.2020": 83.08,
    "Rate.2021": 101.41,
    "Rate.2022": 91.34,
    "Rate.2023": 94.48,
    "Tal_pas": 874.8,
    "kontakt_p_pas": 1.5933
  },
  {
    "bohf": "Diakonhjemmet",
    "Snitt_kontaktar": 2334.2,
    "Snitt_innbyggarar": 25931,
    "Snittrate": 94.59,
    "Rate.2019": 68.74,
    "Rate.2020": 85.53,
    "Rate.2021": 100.28,
    "Rate.2022": 104.07,
    "Rate.2023": 114.34,
    "Tal_pas": 1289.2,
    "kontakt_p_pas": 1.8106
  },
  {
    "bohf": "Innlandet",
    "Snitt_kontaktar": 6439,
    "Snitt_innbyggarar": 63506.8,
    "Snittrate": 98.54,
    "Rate.2019": 81.23,
    "Rate.2020": 86.99,
    "Rate.2021": 105.46,
    "Rate.2022": 106.88,
    "Rate.2023": 112.15,
    "Tal_pas": 3675.4,
    "kontakt_p_pas": 1.7519
  },
  {
    "bohf": "Telemark",
    "Snitt_kontaktar": 3429,
    "Snitt_innbyggarar": 33769,
    "Snittrate": 98.71,
    "Rate.2019": 82.5,
    "Rate.2020": 94.89,
    "Rate.2021": 111.04,
    "Rate.2022": 99.44,
    "Rate.2023": 105.66,
    "Tal_pas": 1955.8,
    "kontakt_p_pas": 1.7532
  },
  {
    "bohf": "Lovisenberg",
    "Snitt_kontaktar": 1942.4,
    "Snitt_innbyggarar": 22897,
    "Snittrate": 104.09,
    "Rate.2019": 79.15,
    "Rate.2020": 90.83,
    "Rate.2021": 110.39,
    "Rate.2022": 114.23,
    "Rate.2023": 125.85,
    "Tal_pas": 1110.2,
    "kontakt_p_pas": 1.7496
  },
  {
    "bohf": "OUS",
    "Snitt_kontaktar": 5997.2,
    "Snitt_innbyggarar": 59446.4,
    "Snittrate": 105.81,
    "Rate.2019": 82.09,
    "Rate.2020": 95.77,
    "Rate.2021": 112.59,
    "Rate.2022": 113.19,
    "Rate.2023": 125.42,
    "Tal_pas": 3262.4,
    "kontakt_p_pas": 1.8383
  },
  {
    "bohf": "Akershus",
    "Snitt_kontaktar": 13970.2,
    "Snitt_innbyggarar": 128646.8,
    "Snittrate": 108.06,
    "Rate.2019": 84.91,
    "Rate.2020": 93.3,
    "Rate.2021": 113.83,
    "Rate.2022": 115.88,
    "Rate.2023": 132.37,
    "Tal_pas": 7836.8,
    "kontakt_p_pas": 1.7826
  },
  {
    "bohf": "UNN",
    "Snitt_kontaktar": 4181,
    "Snitt_innbyggarar": 37118.6,
    "Snittrate": 111.39,
    "Rate.2019": 82.2,
    "Rate.2020": 101.88,
    "Rate.2021": 117.05,
    "Rate.2022": 118.33,
    "Rate.2023": 137.51,
    "Tal_pas": 2390.4,
    "kontakt_p_pas": 1.7491
  },
  {
    "bohf": "Bergen",
    "Snitt_kontaktar": 10828.8,
    "Snitt_innbyggarar": 96697.2,
    "Snittrate": 113.5,
    "Rate.2019": 89.64,
    "Rate.2020": 99.75,
    "Rate.2021": 122.03,
    "Rate.2022": 119.63,
    "Rate.2023": 136.47,
    "Tal_pas": 6308.4,
    "kontakt_p_pas": 1.7166
  },
  {
    "bohf": "Fonna",
    "Snitt_kontaktar": 4636.4,
    "Snitt_innbyggarar": 39994,
    "Snittrate": 114.17,
    "Rate.2019": 92.63,
    "Rate.2020": 106.59,
    "Rate.2021": 123.25,
    "Rate.2022": 121.25,
    "Rate.2023": 127.15,
    "Tal_pas": 2557.8,
    "kontakt_p_pas": 1.8127
  },
  {
    "bohf": "Nord-Trøndelag",
    "Snitt_kontaktar": 3334.2,
    "Snitt_innbyggarar": 28257.4,
    "Snittrate": 115.05,
    "Rate.2019": 90.03,
    "Rate.2020": 101.19,
    "Rate.2021": 125.96,
    "Rate.2022": 125.62,
    "Rate.2023": 132.47,
    "Tal_pas": 1812.8,
    "kontakt_p_pas": 1.8393
  },
  {
    "bohf": "Noreg",
    "Snitt_kontaktar": 129461.8,
    "Snitt_innbyggarar": 1114704,
    "Snittrate": 116.09,
    "Rate.2019": 91.45,
    "Rate.2020": 103.85,
    "Rate.2021": 125.92,
    "Rate.2022": 124.28,
    "Rate.2023": 134.92,
    "Tal_pas": 70931.6,
    "kontakt_p_pas": 1.8252
  },
  {
    "bohf": "Vestre Viken",
    "Snitt_kontaktar": 12878,
    "Snitt_innbyggarar": 105821.2,
    "Snittrate": 120.06,
    "Rate.2019": 94.45,
    "Rate.2020": 110.94,
    "Rate.2021": 129.75,
    "Rate.2022": 128.28,
    "Rate.2023": 136.89,
    "Tal_pas": 6851,
    "kontakt_p_pas": 1.8797
  },
  {
    "bohf": "Finnmark",
    "Snitt_kontaktar": 1759.2,
    "Snitt_innbyggarar": 14386.2,
    "Snittrate": 121.4,
    "Rate.2019": 97.95,
    "Rate.2020": 107.55,
    "Rate.2021": 138.6,
    "Rate.2022": 130.74,
    "Rate.2023": 132.17,
    "Tal_pas": 980.2,
    "kontakt_p_pas": 1.7947
  },
  {
    "bohf": "Nordland",
    "Snitt_kontaktar": 3383.4,
    "Snitt_innbyggarar": 27085.6,
    "Snittrate": 123.4,
    "Rate.2019": 92.69,
    "Rate.2020": 103.76,
    "Rate.2021": 133.68,
    "Rate.2022": 138.99,
    "Rate.2023": 147.9,
    "Tal_pas": 1874.2,
    "kontakt_p_pas": 1.8053
  },
  {
    "bohf": "Østfold",
    "Snitt_kontaktar": 8220,
    "Snitt_innbyggarar": 65127.6,
    "Snittrate": 123.54,
    "Rate.2019": 98.17,
    "Rate.2020": 113.73,
    "Rate.2021": 130.69,
    "Rate.2022": 130.36,
    "Rate.2023": 144.74,
    "Tal_pas": 4572,
    "kontakt_p_pas": 1.7979
  },
  {
    "bohf": "Sørlandet",
    "Snitt_kontaktar": 8451,
    "Snitt_innbyggarar": 67155.8,
    "Snittrate": 123.93,
    "Rate.2019": 94.61,
    "Rate.2020": 101.85,
    "Rate.2021": 138.68,
    "Rate.2022": 136.1,
    "Rate.2023": 148.41,
    "Tal_pas": 4447.2,
    "kontakt_p_pas": 1.9003
  },
  {
    "bohf": "St. Olav",
    "Snitt_kontaktar": 8608.2,
    "Snitt_innbyggarar": 67721,
    "Snittrate": 128.69,
    "Rate.2019": 101.54,
    "Rate.2020": 116.8,
    "Rate.2021": 141.83,
    "Rate.2022": 137.96,
    "Rate.2023": 145.31,
    "Tal_pas": 4597,
    "kontakt_p_pas": 1.8726
  },
  {
    "bohf": "Møre og Romsdal",
    "Snitt_kontaktar": 7359.6,
    "Snitt_innbyggarar": 55257.6,
    "Snittrate": 131.03,
    "Rate.2019": 102.08,
    "Rate.2020": 114.49,
    "Rate.2021": 145.33,
    "Rate.2022": 142.31,
    "Rate.2023": 150.94,
    "Tal_pas": 3895.8,
    "kontakt_p_pas": 1.8891
  },
  {
    "bohf": "Vestfold",
    "Snitt_kontaktar": 6693.6,
    "Snitt_innbyggarar": 49969.8,
    "Snittrate": 131.43,
    "Rate.2019": 102.42,
    "Rate.2020": 125.64,
    "Rate.2021": 147.7,
    "Rate.2022": 139.25,
    "Rate.2023": 142.12,
    "Tal_pas": 3623.8,
    "kontakt_p_pas": 1.8471
  },
  {
    "bohf": "Stavanger",
    "Snitt_kontaktar": 11634,
    "Snitt_innbyggarar": 87767,
    "Snittrate": 134.58,
    "Rate.2019": 107.5,
    "Rate.2020": 121.81,
    "Rate.2021": 147.59,
    "Rate.2022": 142.74,
    "Rate.2023": 153.25,
    "Tal_pas": 6105.8,
    "kontakt_p_pas": 1.9054
  }
]
}
  ]
}