{
  "innhold": [
    {
      "type": "barchart",
      "data": "datasett_1",
      "x": [
        "totsnitt"
      ],
      "y": "bohf",
      "xLabel": {
        "nb": "Antall per 1 000 innbyggere",
        "en": "tmp"
      },
      "yLabel": {
        "nb": "Opptaksområder",
        "en": "Referral areas"
      },
      "annualVar": [
        "tot2019",
        "tot2020",
        "tot2021",
        "tot2022"
      ],
      "annualVarLabels": {
        "nb": [
          "2019",
          "2020",
          "2021",
          "2022"
        ],
        "en": [
          "2019",
          "2020",
          "2021",
          "2022"
        ]
      },
      "format": ",.0f"
    },
    {
      "type": "barchart",
      "data": "datasett_1",
      "x": [
        "offsnitt",
        "privsnitt"
      ],
      "xLegend": {
        "nb": [
          "Offentlig",
          "Privat"
        ],
        "en": [
          "Offentlig",
          "Privat"
        ]
      },
      "y": "bohf",
      "xLabel": {
        "nb": "Antall per 1 000 innbyggere",
        "en": "tmp"
      },
      "yLabel": {
        "nb": "Opptaksområder",
        "en": "Referral areas"
      }
    },
    {
      "type": "table",
      "data": "datasett_1",
      "caption": {
        "nb": "Årlige gjennomsnittsverdier for perioden 2019–2022. Rate pr. 1 000 innbyggere",
        "en": "Årlige gjennomsnittsverdier for perioden 2019–2022. Rate pr. 1 000 innbyggere"
      },
      "columns": [
        {
          "id": "bohf",
          "label_no": "Opptaksområder",
          "label_en": "Referral areas",
          "typeVar": "string",
          "format": ""
        },
        {
          "id": "totsnitt",
          "label_no": "Rate",
          "label_en": "Rate",
          "typeVar": "number",
          "format": ",.0f"
        },
        {
          "id": "tot_pr_pas",
          "label_no": "Konsultasjoner pr. pas.",
          "label_en": "Consultations per patient",
          "typeVar": "number",
          "format": ",.2f"
        }
      ]
    },
    {
      "type": "map",
      "data": "datasett_1",
      "x": "totsnitt",
      "caption": {
        "nb": "Antall per 1 000 innbyggere",
        "en": "tmp"
      },
      "jenks": [
        {
          "cluster": 1,
          "max": 14.9039927706,
          "min": 14.9039927706,
          "lag_min": 28.2606599987,
          "grense": 21.5823263847
        },
        {
          "cluster": 2,
          "max": 32.3323048251,
          "min": 28.2606599987,
          "lag_min": 42.6013825954,
          "grense": 37.4668437103
        },
        {
          "cluster": 3,
          "max": 46.9747995934,
          "min": 42.6013825954,
          "lag_min": 52.9883632695,
          "grense": 49.9815814314
        }
      ],
      "format": ",.0f"
    },
    {
      "type": "data",
      "label": "datasett_1",
      "national": "Norge",
      "description": "Hoveddatasettet for gitt resultatboks",
      "data": [
        {
          "bohf": "Finnmark",
          "tot2018": 17.2560307171,
          "tot2019": 16.5566882577,
          "tot2020": 11.6003709177,
          "tot2021": 14.6055458943,
          "tot2022": 14.4141048008,
          "totsnitt": 14.9039927706,
          "tot_events": 114.4,
          "tot_pas": 113.8,
          "tot_pop": 75263.4,
          "tot_pr_pas": 1.00527240773,
          "off2018": 12.3402270745,
          "off2019": 11.8204422777,
          "off2020": 9.22159555937,
          "off2021": 10.8640920498,
          "off2022": 10.4278275271,
          "offsnitt": 10.9348991744,
          "off_events": 83.8,
          "off_pas": 83.6,
          "off_pop": 75263.4,
          "off_pr_pas": 1.0023923445,
          "priv2018": 4.91580364268,
          "priv2019": 4.73624597998,
          "priv2020": 2.37877535829,
          "priv2021": 3.74145384453,
          "priv2022": 3.98627727368,
          "privsnitt": 3.96909359619,
          "priv_events": 30.6,
          "priv_pas": 30.4,
          "priv_pop": 75263.4,
          "priv_pr_pas": 1.00657894737
        },
        {
          "bohf": "UNN",
          "tot2018": 31.7482070104,
          "tot2019": 29.7039682964,
          "tot2020": 41.5660443198,
          "tot2021": 58.3243497723,
          "tot2022": 57.9146137315,
          "totsnitt": 43.8753488944,
          "tot_events": 870.8,
          "tot_pas": 859,
          "tot_pop": 193459,
          "tot_pr_pas": 1.01373690338,
          "off2018": 3.64399774224,
          "off2019": 2.58413498051,
          "off2020": 2.60044430206,
          "off2021": 3.85432880689,
          "off2022": 2.84396290202,
          "offsnitt": 3.09808969783,
          "off_events": 60.4,
          "off_pas": 58.4,
          "off_pop": 193459,
          "off_pr_pas": 1.03424657534,
          "priv2018": 28.1042092681,
          "priv2019": 27.1198333159,
          "priv2020": 38.9656000177,
          "priv2021": 54.4700209655,
          "priv2022": 55.0706508294,
          "privsnitt": 40.7772591965,
          "priv_events": 810.4,
          "priv_pas": 802.4,
          "priv_pop": 193459,
          "priv_pr_pas": 1.00997008973
        },
        {
          "bohf": "Nordland",
          "tot2018": 28.1474037333,
          "tot2019": 32.5916326855,
          "tot2020": 27.665876448,
          "tot2021": 34.3337757156,
          "tot2022": 32.0402528442,
          "totsnitt": 30.9618131937,
          "tot_events": 440.6,
          "tot_pas": 431.6,
          "tot_pop": 137648.4,
          "tot_pr_pas": 1.02085264133,
          "off2018": 4.86681008026,
          "off2019": 7.17697949201,
          "off2020": 6.35584213076,
          "off2021": 5.06425891917,
          "off2022": 4.73890104605,
          "offsnitt": 5.64123504205,
          "off_events": 79.2,
          "off_pas": 78.6,
          "off_pop": 137648.4,
          "off_pr_pas": 1.00763358779,
          "priv2018": 23.280593653,
          "priv2019": 25.4146531935,
          "priv2020": 21.3100343173,
          "priv2021": 29.2695167964,
          "priv2022": 27.3013517981,
          "privsnitt": 25.3205781517,
          "priv_events": 361.4,
          "priv_pas": 354.6,
          "priv_pop": 137648.4,
          "priv_pr_pas": 1.01917653694
        },
        {
          "bohf": "Helgeland",
          "tot2018": 26.5884969929,
          "tot2019": 25.4463888831,
          "tot2020": 27.6978444891,
          "tot2021": 34.3126241183,
          "tot2022": 27.2565135314,
          "totsnitt": 28.2606599987,
          "tot_events": 228.2,
          "tot_pas": 223.2,
          "tot_pop": 77916.8,
          "tot_pr_pas": 1.02240143369,
          "off2018": 24.948250995,
          "off2019": 23.8338569263,
          "off2020": 25.9934041783,
          "off2021": 33.7495719124,
          "off2022": 25.5241446112,
          "offsnitt": 26.8070032549,
          "off_events": 216.4,
          "off_pas": 211.4,
          "off_pop": 77916.8,
          "off_pr_pas": 1.02365184484,
          "priv2018": 1.64024599785,
          "priv2019": 1.61253195678,
          "priv2020": 1.70444031085,
          "priv2021": 0.563052205967,
          "priv2022": 1.73236892023,
          "privsnitt": 1.4536567438,
          "priv_events": 11.8,
          "priv_pas": 11.8,
          "priv_pop": 77916.8,
          "priv_pr_pas": 1
        },
        {
          "bohf": "Nord-Trøndelag",
          "tot2018": 29.1506110732,
          "tot2019": 34.6161825138,
          "tot2020": 34.5011163362,
          "tot2021": 33.5402866672,
          "tot2022": 29.6743177379,
          "totsnitt": 32.3323048251,
          "tot_events": 443.6,
          "tot_pas": 435.6,
          "tot_pop": 135042.4,
          "tot_pr_pas": 1.01836547291,
          "off2018": 19.0985260524,
          "off2019": 21.5315571133,
          "off2020": 20.119718258,
          "off2021": 19.417821731,
          "off2022": 18.3659485345,
          "offsnitt": 19.7207241517,
          "off_events": 270.8,
          "off_pas": 265,
          "off_pop": 135042.4,
          "off_pr_pas": 1.02188679245,
          "priv2018": 10.0520850208,
          "priv2019": 13.0846254005,
          "priv2020": 14.3813980782,
          "priv2021": 14.1224649363,
          "priv2022": 11.3083692033,
          "privsnitt": 12.6115806734,
          "priv_events": 172.8,
          "priv_pas": 170.8,
          "priv_pop": 135042.4,
          "priv_pr_pas": 1.01170960187
        },
        {
          "bohf": "St. Olav",
          "tot2018": 41.7708023074,
          "tot2019": 47.0160441647,
          "tot2020": 46.5875002221,
          "tot2021": 48.9744058848,
          "tot2022": 43.4275597522,
          "totsnitt": 45.5630107322,
          "tot_events": 1490.8,
          "tot_pas": 1465,
          "tot_pop": 333346.6,
          "tot_pr_pas": 1.0176109215,
          "off2018": 6.88428129484,
          "off2019": 7.07333167268,
          "off2020": 5.84200340777,
          "off2021": 8.06743008521,
          "off2022": 6.40421211329,
          "offsnitt": 6.86079749657,
          "off_events": 225.8,
          "off_pas": 219.6,
          "off_pop": 333346.6,
          "off_pr_pas": 1.02823315118,
          "priv2018": 34.8865210125,
          "priv2019": 39.942712492,
          "priv2020": 40.7454968143,
          "priv2021": 40.9069757996,
          "priv2022": 37.0233476389,
          "privsnitt": 38.7022132356,
          "priv_events": 1265,
          "priv_pas": 1250,
          "priv_pop": 333346.6,
          "priv_pr_pas": 1.012
        },
        {
          "bohf": "Møre og Romsdal",
          "tot2018": 37.128784322,
          "tot2019": 45.3006997217,
          "tot2020": 47.8810641643,
          "tot2021": 53.4943753082,
          "tot2022": 49.7145122352,
          "totsnitt": 46.7637948212,
          "tot_events": 1261.4,
          "tot_pas": 1238,
          "tot_pop": 265204.2,
          "tot_pr_pas": 1.01890145396,
          "off2018": 22.2645401305,
          "off2019": 28.4422354659,
          "off2020": 28.787907717,
          "off2021": 34.0695508671,
          "off2022": 29.3441954813,
          "offsnitt": 28.6197328067,
          "off_events": 771.4,
          "off_pas": 754.6,
          "off_pop": 265204.2,
          "off_pr_pas": 1.02226345083,
          "priv2018": 14.8642441915,
          "priv2019": 16.8584642558,
          "priv2020": 19.0931564473,
          "priv2021": 19.4248244411,
          "priv2022": 20.3703167539,
          "privsnitt": 18.1440620145,
          "priv_events": 490,
          "priv_pas": 486.8,
          "priv_pop": 265204.2,
          "priv_pr_pas": 1.0065735415
        },
        {
          "bohf": "Førde",
          "tot2018": 25.2192122717,
          "tot2019": 21.8264983615,
          "tot2020": 37.2816002218,
          "tot2021": 38.2097237693,
          "tot2022": 31.7002102396,
          "totsnitt": 30.8637024498,
          "tot_events": 336.6,
          "tot_pas": 332.6,
          "tot_pop": 108588.2,
          "tot_pr_pas": 1.01202645821,
          "off2018": 12.4440010635,
          "off2019": 12.9219493263,
          "off2020": 30.184305851,
          "off2021": 29.134740651,
          "off2022": 22.2272746117,
          "offsnitt": 21.4027768224,
          "off_events": 233.6,
          "off_pas": 231,
          "off_pop": 108588.2,
          "off_pr_pas": 1.01125541126,
          "priv2018": 12.7752112082,
          "priv2019": 8.90454903518,
          "priv2020": 7.0972943708,
          "priv2021": 9.07498311823,
          "priv2022": 9.47293562793,
          "privsnitt": 9.46092562748,
          "priv_events": 103,
          "priv_pas": 102.6,
          "priv_pop": 108588.2,
          "priv_pr_pas": 1.00389863548
        },
        {
          "bohf": "Bergen",
          "tot2018": 50.9640610924,
          "tot2019": 54.7957173999,
          "tot2020": 53.177511384,
          "tot2021": 55.4282963123,
          "tot2022": 52.9784123206,
          "totsnitt": 53.4979325017,
          "tot_events": 2371,
          "tot_pas": 2330,
          "tot_pop": 455966.6,
          "tot_pr_pas": 1.01759656652,
          "off2018": 9.17940909406,
          "off2019": 8.86003196397,
          "off2020": 7.86046545387,
          "off2021": 6.91330677654,
          "off2022": 6.69326407711,
          "offsnitt": 7.87917322204,
          "off_events": 356.2,
          "off_pas": 351.8,
          "off_pop": 455966.6,
          "off_pr_pas": 1.01250710631,
          "priv2018": 41.7846519983,
          "priv2019": 45.9356854359,
          "priv2020": 45.3170459301,
          "priv2021": 48.5149895357,
          "priv2022": 46.2851482435,
          "privsnitt": 45.6187592797,
          "priv_events": 2014.8,
          "priv_pas": 1988,
          "priv_pop": 455966.6,
          "priv_pr_pas": 1.01348088531
        },
        {
          "bohf": "Fonna",
          "tot2018": 53.739045083,
          "tot2019": 53.1717115758,
          "tot2020": 52.8175833103,
          "tot2021": 59.1268515127,
          "tot2022": 61.6396219901,
          "totsnitt": 56.1173610674,
          "tot_events": 1010.2,
          "tot_pas": 997,
          "tot_pop": 180623.6,
          "tot_pr_pas": 1.01323971916,
          "off2018": 2.91104207629,
          "off2019": 3.05744332897,
          "off2020": 2.46510750288,
          "off2021": 2.26740816376,
          "off2022": 2.97889473036,
          "offsnitt": 2.73497832367,
          "off_events": 48.4,
          "off_pas": 47.6,
          "off_pop": 180623.6,
          "off_pr_pas": 1.01680672269,
          "priv2018": 50.8280030067,
          "priv2019": 50.1142682469,
          "priv2020": 50.3524758074,
          "priv2021": 56.8594433489,
          "priv2022": 58.6607272597,
          "privsnitt": 53.3823827438,
          "priv_events": 961.8,
          "priv_pas": 952,
          "priv_pop": 180623.6,
          "priv_pr_pas": 1.01029411765
        },
        {
          "bohf": "Stavanger",
          "tot2018": 39.5970670062,
          "tot2019": 44.2410072852,
          "tot2020": 41.1137000588,
          "tot2021": 43.7031803824,
          "tot2022": 46.270634453,
          "totsnitt": 43.0764092761,
          "tot_events": 1500.6,
          "tot_pas": 1478.8,
          "tot_pop": 370595.4,
          "tot_pr_pas": 1.01474168245,
          "off2018": 3.55832945595,
          "off2019": 3.13318467562,
          "off2020": 2.772870064,
          "off2021": 3.24919337033,
          "off2022": 3.45838202299,
          "offsnitt": 3.24080649377,
          "off_events": 118.2,
          "off_pas": 114.6,
          "off_pop": 370595.4,
          "off_pr_pas": 1.03141361257,
          "priv2018": 36.0387375503,
          "priv2019": 41.1078226096,
          "priv2020": 38.3408299948,
          "priv2021": 40.4539870121,
          "priv2022": 42.81225243,
          "privsnitt": 39.8356027824,
          "priv_events": 1382.4,
          "priv_pas": 1370,
          "priv_pop": 370595.4,
          "priv_pr_pas": 1.00905109489
        },
        {
          "bohf": "Østfold",
          "tot2018": 49.5022438585,
          "tot2019": 50.1858162208,
          "tot2020": 50.2474521545,
          "tot2021": 53.8394033057,
          "tot2022": 63.8491384147,
          "totsnitt": 53.635551785,
          "tot_events": 1791.6,
          "tot_pas": 1765.4,
          "tot_pop": 317597.6,
          "tot_pr_pas": 1.01484082927,
          "off2018": 3.62202561962,
          "off2019": 3.53179852264,
          "off2020": 3.36781156347,
          "off2021": 3.6179455291,
          "off2022": 2.35994218482,
          "offsnitt": 3.29673400547,
          "off_events": 106.6,
          "off_pas": 103.4,
          "off_pop": 317597.6,
          "off_pr_pas": 1.03094777563,
          "priv2018": 45.8802182389,
          "priv2019": 46.6540176982,
          "priv2020": 46.879640591,
          "priv2021": 50.2214577766,
          "priv2022": 61.4891962299,
          "privsnitt": 50.3388177796,
          "priv_events": 1685,
          "priv_pas": 1666.2,
          "priv_pop": 317597.6,
          "priv_pr_pas": 1.01128315928
        },
        {
          "bohf": "Akershus",
          "tot2018": 48.7601303325,
          "tot2019": 47.527901113,
          "tot2020": 49.1828955883,
          "tot2021": 54.180178082,
          "tot2022": 64.5544538172,
          "totsnitt": 52.9883632695,
          "tot_events": 3063.8,
          "tot_pas": 3009.8,
          "tot_pop": 577585,
          "tot_pr_pas": 1.01794139145,
          "off2018": 5.36538159363,
          "off2019": 5.00175197008,
          "off2020": 6.15967294484,
          "off2021": 6.15505570289,
          "off2022": 6.33139244641,
          "offsnitt": 5.80841982009,
          "off_events": 335.6,
          "off_pas": 324.8,
          "off_pop": 577585,
          "off_pr_pas": 1.03325123153,
          "priv2018": 43.3947487389,
          "priv2019": 42.5261491429,
          "priv2020": 43.0232226435,
          "priv2021": 48.0251223791,
          "priv2022": 58.2230613708,
          "privsnitt": 47.1799434494,
          "priv_events": 2728.2,
          "priv_pas": 2693.8,
          "priv_pop": 577585,
          "priv_pr_pas": 1.01277006459
        },
        {
          "bohf": "OUS",
          "tot2018": 53.2102943217,
          "tot2019": 49.3767434156,
          "tot2020": 49.2553165423,
          "tot2021": 56.0792381567,
          "tot2022": 68.1996028449,
          "totsnitt": 55.3386945373,
          "tot_events": 1401.6,
          "tot_pas": 1380,
          "tot_pop": 277343.6,
          "tot_pr_pas": 1.01565217391,
          "off2018": 4.48044868959,
          "off2019": 4.16392440283,
          "off2020": 4.74382525346,
          "off2021": 4.60528927975,
          "off2022": 4.32711278966,
          "offsnitt": 4.46224527336,
          "off_events": 118.2,
          "off_pas": 116,
          "off_pop": 277343.6,
          "off_pr_pas": 1.01896551724,
          "priv2018": 48.7298456321,
          "priv2019": 45.2128190128,
          "priv2020": 44.5114912889,
          "priv2021": 51.4739488769,
          "priv2022": 63.8724900553,
          "privsnitt": 50.876449264,
          "priv_events": 1283.4,
          "priv_pas": 1268.2,
          "priv_pop": 277343.6,
          "priv_pr_pas": 1.01198549125
        },
        {
          "bohf": "Lovisenberg",
          "tot2018": 43.5622695751,
          "tot2019": 38.7277229455,
          "tot2020": 38.5793683011,
          "tot2021": 53.7247829021,
          "tot2022": 59.195890289,
          "totsnitt": 46.9747995934,
          "tot_events": 592.4,
          "tot_pas": 579.2,
          "tot_pop": 158383.6,
          "tot_pr_pas": 1.02279005525,
          "off2018": 4.98551989405,
          "off2019": 4.08383741892,
          "off2020": 3.92824155058,
          "off2021": 4.46162661678,
          "off2022": 4.46375547976,
          "offsnitt": 4.38144411457,
          "off_events": 62.6,
          "off_pas": 58.6,
          "off_pop": 158383.6,
          "off_pr_pas": 1.06825938567,
          "priv2018": 38.576749681,
          "priv2019": 34.6438855265,
          "priv2020": 34.6511267505,
          "priv2021": 49.2631562853,
          "priv2022": 54.7321348092,
          "privsnitt": 42.5933554788,
          "priv_events": 529.8,
          "priv_pas": 523,
          "priv_pop": 158383.6,
          "priv_pr_pas": 1.01300191205
        },
        {
          "bohf": "Diakonhjemmet",
          "tot2018": 41.644310241,
          "tot2019": 42.3629811004,
          "tot2020": 39.4629177032,
          "tot2021": 49.461697515,
          "tot2022": 52.5785207676,
          "totsnitt": 45.1693171691,
          "tot_events": 641,
          "tot_pas": 631.4,
          "tot_pop": 143065.8,
          "tot_pr_pas": 1.01520430789,
          "off2018": 5.05964955228,
          "off2019": 6.33884704029,
          "off2020": 3.94010160931,
          "off2021": 2.59309736809,
          "off2022": 3.88999998748,
          "offsnitt": 4.34456269445,
          "off_events": 62,
          "off_pas": 58.8,
          "off_pop": 143065.8,
          "off_pr_pas": 1.05442176871,
          "priv2018": 36.5846606887,
          "priv2019": 36.0241340601,
          "priv2020": 35.5228160939,
          "priv2021": 46.8686001469,
          "priv2022": 48.6885207801,
          "privsnitt": 40.8247544746,
          "priv_events": 579,
          "priv_pas": 573.6,
          "priv_pop": 143065.8,
          "priv_pr_pas": 1.00941422594
        },
        {
          "bohf": "Innlandet",
          "tot2018": 41.4182669022,
          "tot2019": 41.0986395629,
          "tot2020": 41.7714635706,
          "tot2021": 47.9044319433,
          "tot2022": 56.8005322871,
          "totsnitt": 45.8260664141,
          "tot_events": 1667.4,
          "tot_pas": 1646,
          "tot_pop": 338587.6,
          "tot_pr_pas": 1.01300121507,
          "off2018": 3.83934744348,
          "off2019": 4.6201789457,
          "off2020": 4.42864255325,
          "off2021": 5.73827667346,
          "off2022": 7.26021280346,
          "offsnitt": 5.18122498514,
          "off_events": 185,
          "off_pas": 179.4,
          "off_pop": 338587.6,
          "off_pr_pas": 1.03121516165,
          "priv2018": 37.5789194588,
          "priv2019": 36.4784606172,
          "priv2020": 37.3428210174,
          "priv2021": 42.1661552699,
          "priv2022": 49.5403194836,
          "privsnitt": 40.6448414289,
          "priv_events": 1482.4,
          "priv_pas": 1470.2,
          "priv_pop": 338587.6,
          "priv_pr_pas": 1.00829819072
        },
        {
          "bohf": "Vestre Viken",
          "tot2018": 39.3174927584,
          "tot2019": 40.7781316424,
          "tot2020": 38.9810370175,
          "tot2021": 44.8956498719,
          "tot2022": 48.7069547319,
          "totsnitt": 42.6013825954,
          "tot_events": 2134.6,
          "tot_pas": 2107.8,
          "tot_pop": 488231.4,
          "tot_pr_pas": 1.01271467881,
          "off2018": 3.54032376235,
          "off2019": 3.60170211696,
          "off2020": 3.60867106516,
          "off2021": 3.87889664108,
          "off2022": 3.46616609133,
          "offsnitt": 3.62345905207,
          "off_events": 180.2,
          "off_pas": 177.2,
          "off_pop": 488231.4,
          "off_pr_pas": 1.01693002257,
          "priv2018": 35.777168996,
          "priv2019": 37.1764295254,
          "priv2020": 35.3723659524,
          "priv2021": 41.0167532309,
          "priv2022": 45.2407886406,
          "privsnitt": 38.9779235433,
          "priv_events": 1954.4,
          "priv_pas": 1933.4,
          "priv_pop": 488231.4,
          "priv_pr_pas": 1.01086169442
        },
        {
          "bohf": "Vestfold",
          "tot2018": 44.3163950295,
          "tot2019": 41.5463540681,
          "tot2020": 41.0924652104,
          "tot2021": 49.0212687026,
          "tot2022": 52.2416888486,
          "totsnitt": 45.6965342135,
          "tot_events": 1195.2,
          "tot_pas": 1179.6,
          "tot_pop": 246406,
          "tot_pr_pas": 1.01322482197,
          "off2018": 1.62073858774,
          "off2019": 1.45704587621,
          "off2020": 1.01545556859,
          "off2021": 1.73509475022,
          "off2022": 1.27662589916,
          "offsnitt": 1.4169062974,
          "off_events": 36,
          "off_pas": 34.6,
          "off_pop": 246406,
          "off_pr_pas": 1.04046242775,
          "priv2018": 42.6956564418,
          "priv2019": 40.0893081918,
          "priv2020": 40.0770096418,
          "priv2021": 47.2861739524,
          "priv2022": 50.9650629494,
          "privsnitt": 44.2796279161,
          "priv_events": 1159.2,
          "priv_pas": 1146.8,
          "priv_pop": 246406,
          "priv_pr_pas": 1.0108126962
        },
        {
          "bohf": "Telemark",
          "tot2018": 33.1450506874,
          "tot2019": 28.0140397347,
          "tot2020": 30.709673637,
          "tot2021": 26.9818992389,
          "tot2022": 37.278994282,
          "totsnitt": 31.2398778477,
          "tot_events": 572.4,
          "tot_pas": 567.4,
          "tot_pop": 173513.6,
          "tot_pr_pas": 1.00881212548,
          "off2018": 2.20431719635,
          "off2019": 2.64938131015,
          "off2020": 2.47994940958,
          "off2021": 2.9849168451,
          "off2022": 2.68279098833,
          "offsnitt": 2.60095735848,
          "off_events": 47,
          "off_pas": 45.6,
          "off_pop": 173513.6,
          "off_pr_pas": 1.03070175439,
          "priv2018": 30.940733491,
          "priv2019": 25.3646584246,
          "priv2020": 28.2297242274,
          "priv2021": 23.9969823938,
          "priv2022": 34.5962032937,
          "privsnitt": 28.6389204892,
          "priv_events": 525.4,
          "priv_pas": 522.2,
          "priv_pop": 173513.6,
          "priv_pr_pas": 1.00612792034
        },
        {
          "bohf": "Sørlandet",
          "tot2018": 28.3336792408,
          "tot2019": 29.6611238205,
          "tot2020": 28.7385870513,
          "tot2021": 32.970132077,
          "tot2022": 39.3714595631,
          "totsnitt": 31.8748509874,
          "tot_events": 978.6,
          "tot_pas": 962.8,
          "tot_pop": 307241.2,
          "tot_pr_pas": 1.01641046946,
          "off2018": 3.23548463579,
          "off2019": 2.76246152978,
          "off2020": 2.65413850307,
          "off2021": 2.45797467997,
          "off2022": 1.99252720433,
          "offsnitt": 2.61204950213,
          "off_events": 80.4,
          "off_pas": 79,
          "off_pop": 307241.2,
          "off_pr_pas": 1.01772151899,
          "priv2018": 25.098194605,
          "priv2019": 26.8986622907,
          "priv2020": 26.0844485482,
          "priv2021": 30.512157397,
          "priv2022": 37.3789323588,
          "privsnitt": 29.2628014853,
          "priv_events": 898.2,
          "priv_pas": 886.4,
          "priv_pop": 307241.2,
          "priv_pr_pas": 1.01331227437
        },
        {
          "bohf": "Norge",
          "tot2018": 40.9152784017,
          "tot2019": 41.8282906161,
          "tot2020": 42.2799384826,
          "tot2021": 47.302913726,
          "tot2022": 50.8347036625,
          "totsnitt": 44.6974285528,
          "tot_events": 24106.8,
          "tot_pas": 23734,
          "tot_pop": 5361610,
          "tot_pr_pas": 1.01570742395,
          "off2018": 6.40474943262,
          "off2019": 6.71332146694,
          "off2020": 6.86860932012,
          "off2021": 7.4250658189,
          "off2022": 6.72085165404,
          "offsnitt": 6.830710608,
          "off_events": 3677.8,
          "off_pas": 3593.6,
          "off_pop": 5361610,
          "off_pr_pas": 1.02343054319,
          "priv2018": 34.5105289691,
          "priv2019": 35.1149691491,
          "priv2020": 35.4113291625,
          "priv2021": 39.8778479071,
          "priv2022": 44.1138520085,
          "privsnitt": 37.8667179448,
          "priv_events": 20429,
          "priv_pas": 20203.2,
          "priv_pop": 5361610,
          "priv_pr_pas": 1.0111764473
        }
      ]
    }
  ]
}
