{
  "innhold": [
    {
      "type": "barchart",
      "data": "datasett_1",
      "x": ["totsnitt"],
      "y": "bohf",
      "xLabel": {
        "nb": "Antall vitamin Dprøver pr. 10 000 innbyggere",
        "en": "tmp"
      },
      "yLabel": {
        "nb": "Opptaksområder",
        "en": "Referral areas"
      },
      "annualVar": ["tot2021", "tot2022", "tot2023"],
      "annualVarLabels": {
        "nb": ["2021", "2022", "2023"],
        "en": ["2021", "2022", "2023"]
      },
      "format": ",.0f"
    },
    {
      "type": "barchart",
      "data": "datasett_2",
      "x": ["totsnitt"],
      "y": "borhf",
      "xLabel": {
        "nb": "Antall vitamin Dprøver pr. 10 000 innbyggere",
        "en": "tmp"
      },
      "yLabel": {
        "nb": "Helseregioner",
        "en": "Health regions"
      },
      "annualVar": ["tot2021", "tot2022", "tot2023"],
      "annualVarLabels": {
        "nb": ["2021", "2022", "2023"],
        "en": ["2021", "2022", "2023"]
      },
      "format": ",.0f"
    },
    {
      "type": "linechart",
      "data": "datasett_3",
      "x": ["alder"],
      "xLabel": {
        "nb": "Alder",
        "en": "Alder"
      },
      "yLabel": {
        "nb": "Andel av befolkningen i alderen med vitamin D prøve",
        "en": "Andel"
      },
      "format_y": ",.1%",
      "linevars": ["Kvinner", "Menn"],
      "linevarsLabels": {
        "nb": ["Kvinner", "Menn"],
        "en": ["Women", "Men"]
      }
    },
    {
      "type": "table",
      "data": "datasett_1",
      "caption": {
        "nb": "Årlige gjennomsnittsverdier for perioden 2021–2023. <br>* Antall pr. 10  000 innbyggere. Ratene er kjønns- og aldersjusterte. <br>** Andelene er basert på kjønns- og aldersjusterte rater.",
        "en": "Årlige gjennomsnittsverdier for perioden 2021–2023. <br>* Antall pr. 10  000 innbyggere. Ratene er kjønns- og aldersjusterte. <br>** Andelene er basert på kjønns- og aldersjusterte rater."
      },
      "columns": [
        {
          "id": "bohf",
          "label_no": "Opptaksområder",
          "label_en": "Referral areas",
          "typeVar": "string",
          "format": ""
        },
        {
          "id": "totsnitt",
          "label_no": "Rate*",
          "label_en": "Rate*",
          "typeVar": "number",
          "format": ",.0f"
        },
        {
          "id": "tot_events",
          "label_no": "Prøver",
          "label_en": "Tests",
          "typeVar": "number",
          "format": ",.0f"
        },
        {
          "id": "tot_pop",
          "label_no": "Innbyggere",
          "label_en": "Inhabitants",
          "typeVar": "number",
          "format": ",.0f"
        },
        {
          "id": "prove_pr_pas",
          "label_no": "Prøver pr. pas.",
          "label_en": "Tests per patient",
          "typeVar": "number",
          "format": ",.2f"
        },
        {
          "id": "andel_priv",
          "label_no": "Andel** privat",
          "label_en": "Proportion** in private",
          "typeVar": "number",
          "format": ",.0%"
        }
      ]
    },
    {
      "type": "map",
      "data": "datasett_1",
      "x": "totsnitt",
      "caption": {
        "nb": "Antall vitamin Dprøver pr. 10 000 innbyggere",
        "en": "tmp"
      },
      "jenks": [
        {
          "cluster": 1,
          "max": 2023.71355312,
          "min": 2023.71355312,
          "lag_min": 2208.29491938,
          "grense": 2116.00423625
        },
        {
          "cluster": 2,
          "max": 2335.04628833,
          "min": 2208.29491938,
          "lag_min": 2884.40492564,
          "grense": 2609.72560699
        },
        {
          "cluster": 3,
          "max": 3761.30576969,
          "min": 2884.40492564,
          "lag_min": 3860.61667336,
          "grense": 3810.96122152
        }
      ],
      "format": ",.0f"
    },
    {
      "type": "data",
      "label": "datasett_1",
      "national": "Norge",
      "description": "Hoveddatasettet for gitt resultatboks",
      "data": [
        {
          "bohf": "Finnmark",
          "tot2021": 1942.09132436,
          "tot2022": 2109.26064247,
          "tot2023": 2021.36936543,
          "totsnitt": 2023.71355312,
          "andel_priv": 0.028650591181,
          "tot_events": 15023.6666667,
          "tot_pas": 11746.3333333,
          "tot_pop": 74308.3333333,
          "prove_pr_pas": 1.27900905247,
          "borhf": null
        },
        {
          "bohf": "UNN",
          "tot2021": 2232.49635671,
          "tot2022": 2394.49982355,
          "tot2023": 2377.96626091,
          "totsnitt": 2335.04628833,
          "andel_priv": 0.0911146604521,
          "tot_events": 45727,
          "tot_pas": 35082.3333333,
          "tot_pop": 192689.666667,
          "prove_pr_pas": 1.3034195749,
          "borhf": null
        },
        {
          "bohf": "Nordland",
          "tot2021": 2068.946146,
          "tot2022": 2293.01691077,
          "tot2023": 2262.88989408,
          "totsnitt": 2208.29491938,
          "andel_priv": 0.111859307148,
          "tot_events": 31053,
          "tot_pas": 24281,
          "tot_pop": 138332.666667,
          "prove_pr_pas": 1.27890119847,
          "borhf": null
        },
        {
          "bohf": "Helgeland",
          "tot2021": 3755.58000131,
          "tot2022": 3784.11169357,
          "tot2023": 3744.89556775,
          "totsnitt": 3761.30576969,
          "andel_priv": 0.0479722564757,
          "tot_events": 30488.3333333,
          "tot_pas": 22210,
          "tot_pop": 77327.6666667,
          "prove_pr_pas": 1.3727300015,
          "borhf": null
        },
        {
          "bohf": "Nord-Trøndelag",
          "tot2021": 2989.80441842,
          "tot2022": 3032.66154186,
          "tot2023": 3232.24686862,
          "totsnitt": 3084.47010214,
          "andel_priv": 0.458352057612,
          "tot_events": 42765,
          "tot_pas": 31623.3333333,
          "tot_pop": 134761.666667,
          "prove_pr_pas": 1.35232423316,
          "borhf": null
        },
        {
          "bohf": "St. Olav",
          "tot2021": 2699.60971368,
          "tot2022": 2887.71598774,
          "tot2023": 3061.7811338,
          "totsnitt": 2884.40492564,
          "andel_priv": 0.521945542813,
          "tot_events": 96684,
          "tot_pas": 73182.3333333,
          "tot_pop": 339813.333333,
          "prove_pr_pas": 1.32113852615,
          "borhf": null
        },
        {
          "bohf": "Møre og Romsdal",
          "tot2021": 3730.12489496,
          "tot2022": 3905.18825902,
          "tot2023": 3945.64601764,
          "totsnitt": 3860.61667336,
          "andel_priv": 0.103621336193,
          "tot_events": 104209.666667,
          "tot_pas": 76607.3333333,
          "tot_pop": 266585.666667,
          "prove_pr_pas": 1.36030928284,
          "borhf": null
        },
        {
          "bohf": "Førde",
          "tot2021": 2994.82153248,
          "tot2022": 3288.56039348,
          "tot2023": 3432.02884011,
          "totsnitt": 3238.9218292,
          "andel_priv": 0.0457596038176,
          "tot_events": 35815,
          "tot_pas": 25582.6666667,
          "tot_pop": 108538.333333,
          "prove_pr_pas": 1.39997133476,
          "borhf": null
        },
        {
          "bohf": "Bergen",
          "tot2021": 3138.61257446,
          "tot2022": 3337.02163459,
          "tot2023": 3327.34342658,
          "totsnitt": 3267.82862957,
          "andel_priv": 0.115444676575,
          "tot_events": 148622.333333,
          "tot_pas": 104347.666667,
          "tot_pop": 461698.666667,
          "prove_pr_pas": 1.42429953712,
          "borhf": null
        },
        {
          "bohf": "Fonna",
          "tot2021": 3522.15792488,
          "tot2022": 3585.94210938,
          "tot2023": 3509.23332617,
          "totsnitt": 3538.65741995,
          "andel_priv": 0.117880377304,
          "tot_events": 64040.6666667,
          "tot_pas": 46807.3333333,
          "tot_pop": 181471.666667,
          "prove_pr_pas": 1.36817592685,
          "borhf": null
        },
        {
          "bohf": "Stavanger",
          "tot2021": 3426.06497318,
          "tot2022": 3384.30950849,
          "tot2023": 3385.59826921,
          "totsnitt": 3398.23197717,
          "andel_priv": 0.182354463364,
          "tot_events": 122485.333333,
          "tot_pas": 91304.3333333,
          "tot_pop": 377328,
          "prove_pr_pas": 1.34150624468,
          "borhf": null
        },
        {
          "bohf": "Østfold",
          "tot2021": 4782.1246653,
          "tot2022": 4671.76986995,
          "tot2023": 4575.75134088,
          "totsnitt": 4674.48132522,
          "andel_priv": 0.255766289754,
          "tot_events": 155210.666667,
          "tot_pas": 109824,
          "tot_pop": 323951.333333,
          "prove_pr_pas": 1.41326728827,
          "borhf": null
        },
        {
          "bohf": "Akershus",
          "tot2021": 3788.41014392,
          "tot2022": 3990.09799243,
          "tot2023": 4135.50707319,
          "totsnitt": 3972.97834759,
          "andel_priv": 0.718784934146,
          "tot_events": 232523.333333,
          "tot_pas": 172510.666667,
          "tot_pop": 594405.333333,
          "prove_pr_pas": 1.34787800561,
          "borhf": null
        },
        {
          "bohf": "OUS",
          "tot2021": 4224.69271058,
          "tot2022": 4562.44923687,
          "tot2023": 4600.66900702,
          "totsnitt": 4463.47726188,
          "andel_priv": 0.887195885855,
          "tot_events": 118991.666667,
          "tot_pas": 86377.3333333,
          "tot_pop": 282430.333333,
          "prove_pr_pas": 1.3775797663,
          "borhf": null
        },
        {
          "bohf": "Lovisenberg",
          "tot2021": 4091.07974998,
          "tot2022": 4154.57454992,
          "tot2023": 4314.2416185,
          "totsnitt": 4186.98406408,
          "andel_priv": 0.842435371951,
          "tot_events": 60414.3333333,
          "tot_pas": 45230.6666667,
          "tot_pop": 163625,
          "prove_pr_pas": 1.33569407187,
          "borhf": null
        },
        {
          "bohf": "Diakonhjemmet",
          "tot2021": 3775.87485782,
          "tot2022": 3882.37848688,
          "tot2023": 4082.88001227,
          "totsnitt": 3913.79743157,
          "andel_priv": 0.836242397921,
          "tot_events": 57147.6666667,
          "tot_pas": 41445.3333333,
          "tot_pop": 145340.333333,
          "prove_pr_pas": 1.37886854974,
          "borhf": null
        },
        {
          "bohf": "Innlandet",
          "tot2021": 3826.07590324,
          "tot2022": 3880.15871588,
          "tot2023": 4020.19873618,
          "totsnitt": 3909.00195432,
          "andel_priv": 0.233634915656,
          "tot_events": 139870,
          "tot_pas": 99452,
          "tot_pop": 339460.666667,
          "prove_pr_pas": 1.40640711097,
          "borhf": null
        },
        {
          "bohf": "Vestre Viken",
          "tot2021": 4103.41716939,
          "tot2022": 4237.54545003,
          "tot2023": 4401.17253146,
          "totsnitt": 4248.00298784,
          "andel_priv": 0.433841686759,
          "tot_events": 211977.666667,
          "tot_pas": 152596.666667,
          "tot_pop": 495858,
          "prove_pr_pas": 1.38913694052,
          "borhf": null
        },
        {
          "bohf": "Vestfold",
          "tot2021": 4103.14562181,
          "tot2022": 4080.13562918,
          "tot2023": 3923.89213962,
          "totsnitt": 4033.52323978,
          "andel_priv": 0.5069696748,
          "tot_events": 104111,
          "tot_pas": 73679,
          "tot_pop": 250921.666667,
          "prove_pr_pas": 1.41303492176,
          "borhf": null
        },
        {
          "bohf": "Telemark",
          "tot2021": 3300.40882754,
          "tot2022": 3490.77671887,
          "tot2023": 3809.47105884,
          "totsnitt": 3534.5557637,
          "andel_priv": 0.104821285404,
          "tot_events": 63877.6666667,
          "tot_pas": 45247.6666667,
          "tot_pop": 174350,
          "prove_pr_pas": 1.4117339384,
          "borhf": null
        },
        {
          "bohf": "Sørlandet",
          "tot2021": 3644.40981234,
          "tot2022": 3724.29053596,
          "tot2023": 3889.62895456,
          "totsnitt": 3753.72209182,
          "andel_priv": 0.117058204672,
          "tot_events": 116646.666667,
          "tot_pas": 82487.6666667,
          "tot_pop": 312009.333333,
          "prove_pr_pas": 1.41411039226,
          "borhf": null
        },
        {
          "bohf": "Norge",
          "tot2021": 3568.97888777,
          "tot2022": 3692.07984119,
          "tot2023": 3766.55258348,
          "totsnitt": 3676.20188421,
          "andel_priv": 0.375072355713,
          "tot_events": 1997725.66667,
          "tot_pas": 1451662.33333,
          "tot_pop": 5435207.66667,
          "prove_pr_pas": 1.37616415388,
          "borhf": null
        }
      ]
    },
    {
      "type": "data",
      "label": "datasett_2",
      "description": "Ekstradatasettet for gitt resultatboks",
      "data": [
        {
          "borhf": "Helse Nord",
          "tot2021": 2393.48571795,
          "tot2022": 2551.84859445,
          "tot2023": 2515.99746414,
          "totsnitt": 2487.04466468,
          "andel_priv": 0.0776117169756,
          "tot_events": 122292,
          "tot_pas": 93268,
          "tot_pop": 482658.333333,
          "prove_pr_pas": 1.31118926105,
          "bohf": null,
          "ermann": null
        },
        {
          "borhf": "Helse Midt-Norge",
          "tot2021": 3125.24809448,
          "tot2022": 3280.53571815,
          "tot2023": 3410.21001379,
          "totsnitt": 3272.62262819,
          "andel_priv": 0.332833978854,
          "tot_events": 243658.666667,
          "tot_pas": 181315.333333,
          "tot_pop": 741160.666667,
          "prove_pr_pas": 1.34383927816,
          "bohf": null,
          "ermann": null
        },
        {
          "borhf": "Helse Vest",
          "tot2021": 3277.92123582,
          "tot2022": 3386.84051595,
          "tot2023": 3385.64992849,
          "totsnitt": 3350.29604415,
          "andel_priv": 0.132036402747,
          "tot_events": 370963.333333,
          "tot_pas": 267863.666667,
          "tot_pop": 1129036.66667,
          "prove_pr_pas": 1.38489604787,
          "bohf": null,
          "ermann": null
        },
        {
          "borhf": "Helse Sør-Øst",
          "tot2021": 3972.64671552,
          "tot2022": 4085.21092075,
          "tot2023": 4188.27681255,
          "totsnitt": 4082.38937001,
          "andel_priv": 0.483031102024,
          "tot_events": 1260811.66667,
          "tot_pas": 905275,
          "tot_pop": 3082352,
          "prove_pr_pas": 1.39273885468,
          "bohf": null,
          "ermann": null
        },
        {
          "borhf": "Norge",
          "tot2021": 3568.97888777,
          "tot2022": 3692.07984119,
          "tot2023": 3766.55258348,
          "totsnitt": 3676.20188421,
          "andel_priv": 0.375072355713,
          "tot_events": 1997725.66667,
          "tot_pas": 1446286,
          "tot_pop": 5435207.66667,
          "prove_pr_pas": 1.38127982063,
          "bohf": null,
          "ermann": null
        }
      ]
    },
    {
      "type": "data",
      "label": "datasett_3",
      "description": "Ekstradatasettet for gitt resultatboks",
      "data": [
        {
          "alder": 0,
          "Kvinner": 0.00945350849182,
          "Menn": 0.0117017084635
        },
        {
          "alder": 1,
          "Kvinner": 0.0247152030203,
          "Menn": 0.0288525718218
        },
        {
          "alder": 2,
          "Kvinner": 0.03050365845,
          "Menn": 0.0359281437126
        },
        {
          "alder": 3,
          "Kvinner": 0.0386552750953,
          "Menn": 0.0445075260922
        },
        {
          "alder": 4,
          "Kvinner": 0.0431940834135,
          "Menn": 0.0500771161776
        },
        {
          "alder": 5,
          "Kvinner": 0.0483795334879,
          "Menn": 0.0528897717249
        },
        {
          "alder": 6,
          "Kvinner": 0.0553074772423,
          "Menn": 0.0572552227536
        },
        {
          "alder": 7,
          "Kvinner": 0.0626864699368,
          "Menn": 0.0633994868044
        },
        {
          "alder": 8,
          "Kvinner": 0.0711539568713,
          "Menn": 0.0726823449216
        },
        {
          "alder": 9,
          "Kvinner": 0.0783443356856,
          "Menn": 0.0789188347281
        },
        {
          "alder": 10,
          "Kvinner": 0.0885536778698,
          "Menn": 0.0875774208769
        },
        {
          "alder": 11,
          "Kvinner": 0.0980696387404,
          "Menn": 0.0915051770078
        },
        {
          "alder": 12,
          "Kvinner": 0.116753678215,
          "Menn": 0.0945319072227
        },
        {
          "alder": 13,
          "Kvinner": 0.152035164161,
          "Menn": 0.106221077818
        },
        {
          "alder": 14,
          "Kvinner": 0.194999162015,
          "Menn": 0.123711403466
        },
        {
          "alder": 15,
          "Kvinner": 0.220575351889,
          "Menn": 0.132445824647
        },
        {
          "alder": 16,
          "Kvinner": 0.233023243694,
          "Menn": 0.125913291571
        },
        {
          "alder": 17,
          "Kvinner": 0.24264282898,
          "Menn": 0.127109524042
        },
        {
          "alder": 18,
          "Kvinner": 0.23183433089,
          "Menn": 0.116500352301
        },
        {
          "alder": 19,
          "Kvinner": 0.216114069747,
          "Menn": 0.109493964993
        },
        {
          "alder": 20,
          "Kvinner": 0.217707450316,
          "Menn": 0.106826435552
        },
        {
          "alder": 21,
          "Kvinner": 0.22296308644,
          "Menn": 0.108304327348
        },
        {
          "alder": 22,
          "Kvinner": 0.224483431276,
          "Menn": 0.112484478418
        },
        {
          "alder": 23,
          "Kvinner": 0.230164523894,
          "Menn": 0.115662868002
        },
        {
          "alder": 24,
          "Kvinner": 0.23409452498,
          "Menn": 0.118915468724
        },
        {
          "alder": 25,
          "Kvinner": 0.243416254761,
          "Menn": 0.122027575374
        },
        {
          "alder": 26,
          "Kvinner": 0.246744190002,
          "Menn": 0.124734265284
        },
        {
          "alder": 27,
          "Kvinner": 0.250686574092,
          "Menn": 0.127028554228
        },
        {
          "alder": 28,
          "Kvinner": 0.254882193206,
          "Menn": 0.127575054855
        },
        {
          "alder": 29,
          "Kvinner": 0.260317935771,
          "Menn": 0.129442212012
        },
        {
          "alder": 30,
          "Kvinner": 0.270107549839,
          "Menn": 0.134590169012
        },
        {
          "alder": 31,
          "Kvinner": 0.278553135626,
          "Menn": 0.136629730837
        },
        {
          "alder": 32,
          "Kvinner": 0.28583469247,
          "Menn": 0.13840346048
        },
        {
          "alder": 33,
          "Kvinner": 0.286127938643,
          "Menn": 0.137775301173
        },
        {
          "alder": 34,
          "Kvinner": 0.287470358192,
          "Menn": 0.139965114719
        },
        {
          "alder": 35,
          "Kvinner": 0.283603570674,
          "Menn": 0.13842227678
        },
        {
          "alder": 36,
          "Kvinner": 0.279267125578,
          "Menn": 0.139877681166
        },
        {
          "alder": 37,
          "Kvinner": 0.274158982438,
          "Menn": 0.141602544485
        },
        {
          "alder": 38,
          "Kvinner": 0.272406842068,
          "Menn": 0.140629027393
        },
        {
          "alder": 39,
          "Kvinner": 0.272795343532,
          "Menn": 0.142762591833
        },
        {
          "alder": 40,
          "Kvinner": 0.274217391819,
          "Menn": 0.148063348821
        },
        {
          "alder": 41,
          "Kvinner": 0.272970821651,
          "Menn": 0.147045501569
        },
        {
          "alder": 42,
          "Kvinner": 0.269571714033,
          "Menn": 0.148540712632
        },
        {
          "alder": 43,
          "Kvinner": 0.263469131109,
          "Menn": 0.147048538839
        },
        {
          "alder": 44,
          "Kvinner": 0.261518123618,
          "Menn": 0.148437028957
        },
        {
          "alder": 45,
          "Kvinner": 0.258450525604,
          "Menn": 0.147617443023
        },
        {
          "alder": 46,
          "Kvinner": 0.258299304713,
          "Menn": 0.150260372921
        },
        {
          "alder": 47,
          "Kvinner": 0.263686937551,
          "Menn": 0.156438232502
        },
        {
          "alder": 48,
          "Kvinner": 0.270382686496,
          "Menn": 0.161479941115
        },
        {
          "alder": 49,
          "Kvinner": 0.276506649874,
          "Menn": 0.168135332564
        },
        {
          "alder": 50,
          "Kvinner": 0.280872862606,
          "Menn": 0.177204989798
        },
        {
          "alder": 51,
          "Kvinner": 0.287696526708,
          "Menn": 0.181790298348
        },
        {
          "alder": 52,
          "Kvinner": 0.291412363283,
          "Menn": 0.187257867504
        },
        {
          "alder": 53,
          "Kvinner": 0.294179418784,
          "Menn": 0.192778464292
        },
        {
          "alder": 54,
          "Kvinner": 0.295923522995,
          "Menn": 0.199986903995
        },
        {
          "alder": 55,
          "Kvinner": 0.298921381337,
          "Menn": 0.207868116654
        },
        {
          "alder": 56,
          "Kvinner": 0.299292767708,
          "Menn": 0.213085013549
        },
        {
          "alder": 57,
          "Kvinner": 0.30073226263,
          "Menn": 0.21875
        },
        {
          "alder": 58,
          "Kvinner": 0.300095461796,
          "Menn": 0.22096233425
        },
        {
          "alder": 59,
          "Kvinner": 0.299684643073,
          "Menn": 0.222566874482
        },
        {
          "alder": 60,
          "Kvinner": 0.299448902639,
          "Menn": 0.228365820844
        },
        {
          "alder": 61,
          "Kvinner": 0.297548758808,
          "Menn": 0.231278147796
        },
        {
          "alder": 62,
          "Kvinner": 0.296798174881,
          "Menn": 0.232858423575
        },
        {
          "alder": 63,
          "Kvinner": 0.297376907477,
          "Menn": 0.238400887515
        },
        {
          "alder": 64,
          "Kvinner": 0.30575731573,
          "Menn": 0.244228260061
        },
        {
          "alder": 65,
          "Kvinner": 0.307880403052,
          "Menn": 0.250058670053
        },
        {
          "alder": 66,
          "Kvinner": 0.316377461079,
          "Menn": 0.253165728278
        },
        {
          "alder": 67,
          "Kvinner": 0.318000954958,
          "Menn": 0.258464681845
        },
        {
          "alder": 68,
          "Kvinner": 0.32142673096,
          "Menn": 0.258841295583
        },
        {
          "alder": 69,
          "Kvinner": 0.323223265858,
          "Menn": 0.26050686378
        },
        {
          "alder": 70,
          "Kvinner": 0.323443696671,
          "Menn": 0.264187075608
        },
        {
          "alder": 71,
          "Kvinner": 0.317028743067,
          "Menn": 0.25828182989
        },
        {
          "alder": 72,
          "Kvinner": 0.324445553841,
          "Menn": 0.26607639569
        },
        {
          "alder": 73,
          "Kvinner": 0.342465007353,
          "Menn": 0.279396339331
        },
        {
          "alder": 74,
          "Kvinner": 0.362617373777,
          "Menn": 0.30323645684
        },
        {
          "alder": 75,
          "Kvinner": 0.38666784312,
          "Menn": 0.327830502672
        },
        {
          "alder": 76,
          "Kvinner": 0.418223907797,
          "Menn": 0.353625763946
        },
        {
          "alder": 77,
          "Kvinner": 0.429830406466,
          "Menn": 0.36657685183
        },
        {
          "alder": 78,
          "Kvinner": 0.417635806743,
          "Menn": 0.356972972973
        },
        {
          "alder": 79,
          "Kvinner": 0.410136910175,
          "Menn": 0.363340726532
        },
        {
          "alder": 80,
          "Kvinner": 0.392993518053,
          "Menn": 0.339547535328
        },
        {
          "alder": 81,
          "Kvinner": 0.395583051579,
          "Menn": 0.335253851572
        },
        {
          "alder": 82,
          "Kvinner": 0.401199186045,
          "Menn": 0.348794438044
        },
        {
          "alder": 83,
          "Kvinner": 0.417267520216,
          "Menn": 0.363477391956
        },
        {
          "alder": 84,
          "Kvinner": 0.41783133414,
          "Menn": 0.365158185727
        },
        {
          "alder": 85,
          "Kvinner": 0.402949748645,
          "Menn": 0.354837785986
        },
        {
          "alder": 86,
          "Kvinner": 0.393681043129,
          "Menn": 0.352167732765
        },
        {
          "alder": 87,
          "Kvinner": 0.380308491347,
          "Menn": 0.351327787263
        },
        {
          "alder": 88,
          "Kvinner": 0.384718892205,
          "Menn": 0.351119121469
        },
        {
          "alder": 89,
          "Kvinner": 0.389678222511,
          "Menn": 0.369430205047
        },
        {
          "alder": 90,
          "Kvinner": 0.398491339169,
          "Menn": 0.366564139678
        },
        {
          "alder": 91,
          "Kvinner": 0.398363773368,
          "Menn": 0.373268493958
        },
        {
          "alder": 92,
          "Kvinner": 0.403190624866,
          "Menn": 0.379084355397
        },
        {
          "alder": 93,
          "Kvinner": 0.391087838185,
          "Menn": 0.37547055252
        },
        {
          "alder": 94,
          "Kvinner": 0.392170636695,
          "Menn": 0.387313555155
        },
        {
          "alder": 95,
          "Kvinner": 0.386924075276,
          "Menn": 0.378875110717
        }
      ]
    }
  ]
}
