{
  "innhold": [
    {
      "type": "barchart",
      "data": "datasett_1",
      "x": [
        "totsnitt"
      ],
      "y": "bohf",
      "xLabel": {
        "nb": "Antall Gamma GT-prøver pr. 1000 innbyggere",
        "en": "Number of GGT tests pr. 1000 population"
      },
      "yLabel": {
        "nb": "Opptaksområder",
        "en": "Referral areas"
      },
      "annualVar": [
        "tot2021",
        "tot2022",
        "tot2023"
      ],
      "annualVarLabels": {
        "nb": [
          "2021",
          "2022",
          "2023"
        ],
        "en": [
          "2021",
          "2022",
          "2023"
        ]
      },
      "format": ",.0f"
    },
    {
      "type": "barchart",
      "data": "datasett_2",
      "x": [
        "totsnitt"
      ],
      "y": "borhf",
      "xLabel": {
        "nb": "Antall Gamma GT-prøver pr. 1000 innbyggere",
        "en": "Number of GGT tests pr. 1000 population"
      },
      "yLabel": {
        "nb": "Regionale helseforetak (RHF)",
        "en": "Regional health authorities"
      },
      "annualVar": [
        "tot2021",
        "tot2022",
        "tot2023"
      ],
      "annualVarLabels": {
        "nb": [
          "2021",
          "2022",
          "2023"
        ],
        "en": [
          "2021",
          "2022",
          "2023"
        ]
      },
      "format": ",.0f"
    },
    {
      "type": "linechart",
      "data": "datasett_3",
      "linevars": [
        "kvinner",
        "menn"
      ],
      "linecolors": [
        "#253776",
        "#74A5CD"
      ],
      "linevarsLabels": {
        "nb": [
          "Kvinner",
          "Menn"
        ],
        "en": [
          "Women",
          "Men"
        ]
      },
      "x": [
        "alder"
      ],
      "y": "pctandel",
      "xLabel": {
        "nb": "Alder",
        "en": "Age"
      },
      "yLabel": {
        "nb": "Andel av befolkningen som fikk tatt Gamma GT-prøve",
        "en": "Proportion of population that received GGT test"
      },
      "format_y": ",.0%"
    },
    {
      "type": "table",
      "data": "datasett_1",
      "caption": {
        "nb": "Årlige gjennomsnittsverdier for perioden 2021–2023. <br>* Antall pr. 1000 innbyggere. Ratene er kjønns- og aldersjusterte. <br>** Andelene er basert på kjønns- og aldersjusterte rater.",
        "en": "Annual average during 2021–2023. <br>* Rate per 1000 population. Rates are gender- and age-adjusted. <br>** Proportions are based on adjusted rates."
      },
      "columns": [
        {
          "id": "bohf",
          "label_no": "Opptaksområder",
          "label_en": "Referral areas",
          "typeVar": "string",
          "format": ""
        },
        {
          "id": "totsnitt",
          "label_no": "Rate*",
          "label_en": "Rate*",
          "typeVar": "number",
          "format": ",.0f"
        },
        {
          "id": "tot_events",
          "label_no": "Prøver",
          "label_en": "Tests",
          "typeVar": "number",
          "format": ",.0f"
        },
        {
          "id": "tot_pop",
          "label_no": "Innbyggere",
          "label_en": "Inhabitants",
          "typeVar": "number",
          "format": ",.0f"
        },
        {
          "id": "prove_pr_pas",
          "label_no": "Prøver pr. pas.",
          "label_en": "Tests per patient",
          "typeVar": "number",
          "format": ",.2f"
        },
        {
          "id": "andel_priv",
          "label_no": "Andel** privat",
          "label_en": "Proportion** in private",
          "typeVar": "number",
          "format": ",.0%"
        }
      ]
    },
    {
      "type": "map",
      "data": "datasett_1",
      "x": "totsnitt",
      "caption": {
        "nb": "Antall Gamma GT-prøver pr. 1000 innbyggere",
        "en": "Number of GGT tests pr. 1000 population"
      },
      "jenks": [
        {
          "cluster": 1,
          "max": 254.857427498,
          "min": 219.439565412,
          "lag_min": 259.151839095,
          "grense": 257.004633296
        },
        {
          "cluster": 2,
          "max": 305.668949866,
          "min": 259.151839095,
          "lag_min": 313.822368784,
          "grense": 309.745659325
        },
        {
          "cluster": 3,
          "max": 396.150764459,
          "min": 313.822368784,
          "lag_min": 440.576848099,
          "grense": 418.363806279
        }
      ],
      "format": ",.0f"
    },
    {
      "type": "data",
      "label": "datasett_1",
      "national": "Norge",
      "description": "Hoveddatasettet for gitt resultatboks",
      "data": [
        {
          "bohf": "Finnmark",
          "andel_priv": 0.0152829119819,
          "tot2021": 263.925257112,
          "tot2022": 276.096129838,
          "tot2023": 273.611834632,
          "totsnitt": 271.14624432,
          "tot_events": 20627.6666667,
          "tot_pas": 14350,
          "tot_pop": 74308.3333333,
          "prove_pr_pas": 1.43746806039
        },
        {
          "bohf": "UNN",
          "andel_priv": 0.0723503901211,
          "tot2021": 271.039940614,
          "tot2022": 279.599013179,
          "tot2023": 282.855522109,
          "totsnitt": 277.811250772,
          "tot_events": 55225,
          "tot_pas": 38586.6666667,
          "tot_pop": 192689.666667,
          "prove_pr_pas": 1.43119384934
        },
        {
          "bohf": "Nordland",
          "andel_priv": 0.118345185654,
          "tot2021": 259.387910828,
          "tot2022": 274.405628442,
          "tot2023": 256.796907623,
          "totsnitt": 263.459068012,
          "tot_events": 38193,
          "tot_pas": 26884.6666667,
          "tot_pop": 138332.666667,
          "prove_pr_pas": 1.42062389962
        },
        {
          "bohf": "Helgeland",
          "andel_priv": 0.0445747413278,
          "tot2021": 327.683564898,
          "tot2022": 313.393456236,
          "tot2023": 300.62655578,
          "totsnitt": 313.822368784,
          "tot_events": 26105,
          "tot_pas": 17871.3333333,
          "tot_pop": 77327.6666667,
          "prove_pr_pas": 1.46071921513
        },
        {
          "bohf": "Nord-Trøndelag",
          "andel_priv": 0.595395197628,
          "tot2021": 211.899533985,
          "tot2022": 219.261515471,
          "tot2023": 227.359501084,
          "totsnitt": 219.439565412,
          "tot_events": 30860,
          "tot_pas": 22628.3333333,
          "tot_pop": 134761.666667,
          "prove_pr_pas": 1.36377697577
        },
        {
          "bohf": "St. Olav",
          "andel_priv": 0.512473181876,
          "tot2021": 249.527986275,
          "tot2022": 253.507106537,
          "tot2023": 261.468733766,
          "totsnitt": 254.857427498,
          "tot_events": 84799.3333333,
          "tot_pas": 60432.6666667,
          "tot_pop": 339813.333333,
          "prove_pr_pas": 1.4032035654
        },
        {
          "bohf": "Møre og Romsdal",
          "andel_priv": 0.106791434936,
          "tot2021": 260.619987029,
          "tot2022": 257.447784652,
          "tot2023": 259.572594943,
          "totsnitt": 259.151839095,
          "tot_events": 71257.3333333,
          "tot_pas": 50132,
          "tot_pop": 266585.666667,
          "prove_pr_pas": 1.42139418602
        },
        {
          "bohf": "Førde",
          "andel_priv": 0.042424101662,
          "tot2021": 240.16135807,
          "tot2022": 247.863378232,
          "tot2023": 254.205571276,
          "totsnitt": 247.381152574,
          "tot_events": 28104,
          "tot_pas": 19280,
          "tot_pop": 108538.333333,
          "prove_pr_pas": 1.45767634855
        },
        {
          "bohf": "Bergen",
          "andel_priv": 0.109180064028,
          "tot2021": 332.114153184,
          "tot2022": 327.000019893,
          "tot2023": 316.827494023,
          "totsnitt": 325.124918352,
          "tot_events": 145796,
          "tot_pas": 92897.6666667,
          "tot_pop": 461698.666667,
          "prove_pr_pas": 1.56942585569
        },
        {
          "bohf": "Fonna",
          "andel_priv": 0.152820559791,
          "tot2021": 450.861434829,
          "tot2022": 444.962193606,
          "tot2023": 426.376497218,
          "totsnitt": 440.576848099,
          "tot_events": 80739,
          "tot_pas": 50206.6666667,
          "tot_pop": 181471.666667,
          "prove_pr_pas": 1.60813305006
        },
        {
          "bohf": "Stavanger",
          "andel_priv": 0.193386606234,
          "tot2021": 327.030656348,
          "tot2022": 319.481023241,
          "tot2023": 321.145508673,
          "totsnitt": 322.428667983,
          "tot_events": 112334.666667,
          "tot_pas": 74104.3333333,
          "tot_pop": 377328,
          "prove_pr_pas": 1.51589875536
        },
        {
          "bohf": "Østfold",
          "andel_priv": 0.244571068814,
          "tot2021": 383.763092146,
          "tot2022": 377.713168625,
          "tot2023": 376.257574318,
          "totsnitt": 379.104129304,
          "tot_events": 127290.333333,
          "tot_pas": 83710.6666667,
          "tot_pop": 323951.333333,
          "prove_pr_pas": 1.52059872896
        },
        {
          "bohf": "Akershus",
          "andel_priv": 0.742040296918,
          "tot2021": 325.797293376,
          "tot2022": 334.710540764,
          "tot2023": 331.404577488,
          "totsnitt": 330.589437112,
          "tot_events": 191535.333333,
          "tot_pas": 131021.333333,
          "tot_pop": 594405.333333,
          "prove_pr_pas": 1.46186371685
        },
        {
          "bohf": "OUS",
          "andel_priv": 0.949030746706,
          "tot2021": 329.588963612,
          "tot2022": 346.300157169,
          "tot2023": 335.306644823,
          "totsnitt": 336.996490186,
          "tot_events": 85720.3333333,
          "tot_pas": 59126,
          "tot_pop": 282430.333333,
          "prove_pr_pas": 1.44979084216
        },
        {
          "bohf": "Lovisenberg",
          "andel_priv": 0.899463858841,
          "tot2021": 294.251334149,
          "tot2022": 297.210776455,
          "tot2023": 292.187490318,
          "totsnitt": 294.432095934,
          "tot_events": 39212,
          "tot_pas": 28648,
          "tot_pop": 163625,
          "prove_pr_pas": 1.36875174532
        },
        {
          "bohf": "Diakonhjemmet",
          "andel_priv": 0.944198207286,
          "tot2021": 308.215062813,
          "tot2022": 303.84501063,
          "tot2023": 305.434872155,
          "totsnitt": 305.668949866,
          "tot_events": 43878.3333333,
          "tot_pas": 30663.6666667,
          "tot_pop": 145340.333333,
          "prove_pr_pas": 1.43095520214
        },
        {
          "bohf": "Innlandet",
          "andel_priv": 0.253382703559,
          "tot2021": 300.470165748,
          "tot2022": 299.924538334,
          "tot2023": 302.094539035,
          "totsnitt": 300.799899679,
          "tot_events": 110479.666667,
          "tot_pas": 74664.6666667,
          "tot_pop": 339460.666667,
          "prove_pr_pas": 1.47967802709
        },
        {
          "bohf": "Vestre Viken",
          "andel_priv": 0.449042444781,
          "tot2021": 370.920733965,
          "tot2022": 367.100764672,
          "tot2023": 373.245305515,
          "totsnitt": 370.334520053,
          "tot_events": 185787.333333,
          "tot_pas": 124628,
          "tot_pop": 495858,
          "prove_pr_pas": 1.49073509431
        },
        {
          "bohf": "Vestfold",
          "andel_priv": 0.479275040322,
          "tot2021": 398.097964118,
          "tot2022": 391.831025567,
          "tot2023": 398.905949776,
          "totsnitt": 396.150764459,
          "tot_events": 103642.333333,
          "tot_pas": 68840.6666667,
          "tot_pop": 250921.666667,
          "prove_pr_pas": 1.50553936142
        },
        {
          "bohf": "Telemark",
          "andel_priv": 0.104224871451,
          "tot2021": 268.926780169,
          "tot2022": 266.370298681,
          "tot2023": 263.427633081,
          "totsnitt": 266.148857697,
          "tot_events": 49190,
          "tot_pas": 33677,
          "tot_pop": 174350,
          "prove_pr_pas": 1.46064079342
        },
        {
          "bohf": "Sørlandet",
          "andel_priv": 0.112074676454,
          "tot2021": 489.667141767,
          "tot2022": 474.164586288,
          "tot2023": 462.601076244,
          "totsnitt": 475.204633814,
          "tot_events": 147760.666667,
          "tot_pas": 93085.6666667,
          "tot_pop": 312009.333333,
          "prove_pr_pas": 1.58736217892
        },
        {
          "bohf": "Norge",
          "andel_priv": 0.3626908845,
          "tot2021": 328.109001882,
          "tot2022": 327.979436968,
          "tot2023": 326.414504802,
          "totsnitt": 327.417416555,
          "tot_events": 1778541.33333,
          "tot_pas": 1195443,
          "tot_pop": 5435207.66667,
          "prove_pr_pas": 1.48776757514
        }
      ]
    },
    {
      "type": "data",
      "label": "datasett_2",
      "description": "Ekstradatasettet for gitt resultatboks",
      "data": [
        {
          "borhf": "Helse Nord",
          "andel_priv": 0.0710344994487,
          "tot2021": 275.922690149,
          "tot2022": 283.195030589,
          "tot2023": 276.875341999,
          "totsnitt": 278.611395868,
          "tot_events": 140150.666667,
          "tot_pas": 97646.3333333,
          "tot_pop": 482658.333333,
          "prove_pr_pas": 1.43528857544
        },
        {
          "borhf": "Helse Midt-Norge",
          "andel_priv": 0.372456422201,
          "tot2021": 246.180314465,
          "tot2022": 248.200006679,
          "tot2023": 253.930109176,
          "totsnitt": 249.415684106,
          "tot_events": 186916.666667,
          "tot_pas": 133146.333333,
          "tot_pop": 741160.666667,
          "prove_pr_pas": 1.40384389106
        },
        {
          "borhf": "Helse Vest",
          "andel_priv": 0.140576192119,
          "tot2021": 340.396736136,
          "tot2022": 335.966990765,
          "tot2023": 329.915441712,
          "totsnitt": 335.290721031,
          "tot_events": 366973.666667,
          "tot_pas": 236376.333333,
          "tot_pop": 1129036.66667,
          "prove_pr_pas": 1.55249750045
        },
        {
          "borhf": "Helse Sør-Øst",
          "andel_priv": 0.473412655108,
          "tot2021": 352.68431631,
          "tot2022": 352.221974949,
          "tot2023": 350.992667624,
          "totsnitt": 351.868427443,
          "tot_events": 1084500.33333,
          "tot_pas": 726058,
          "tot_pop": 3082352,
          "prove_pr_pas": 1.493682782
        },
        {
          "borhf": "Norge",
          "andel_priv": 0.3626908845,
          "tot2021": 328.109001882,
          "tot2022": 327.979436968,
          "tot2023": 326.414504802,
          "totsnitt": 327.417416555,
          "tot_events": 1778541.33333,
          "tot_pas": 1192435,
          "tot_pop": 5435207.66667,
          "prove_pr_pas": 1.49152057205
        }
      ]
    },
    {
      "type": "data",
      "label": "datasett_3",
      "description": "Ekstradatasettet for gitt resultatboks",
      "data": [
        {
          "alder": 0,
          "kvinner": 0.00335662673865,
          "menn": 0.00460891103043
        },
        {
          "alder": 1,
          "kvinner": 0.00842547174624,
          "menn": 0.0103629795286
        },
        {
          "alder": 2,
          "kvinner": 0.0116004830575,
          "menn": 0.0129651411463
        },
        {
          "alder": 3,
          "kvinner": 0.0158976428353,
          "menn": 0.0174319504904
        },
        {
          "alder": 4,
          "kvinner": 0.0185370912391,
          "menn": 0.0207148895529
        },
        {
          "alder": 5,
          "kvinner": 0.0212422460108,
          "menn": 0.0225990493295
        },
        {
          "alder": 6,
          "kvinner": 0.0254939114073,
          "menn": 0.0246350364964
        },
        {
          "alder": 7,
          "kvinner": 0.028740798645,
          "menn": 0.0280770041279
        },
        {
          "alder": 8,
          "kvinner": 0.0317739552081,
          "menn": 0.032336400818
        },
        {
          "alder": 9,
          "kvinner": 0.0364152565951,
          "menn": 0.0365061013233
        },
        {
          "alder": 10,
          "kvinner": 0.041183068063,
          "menn": 0.0398795907519
        },
        {
          "alder": 11,
          "kvinner": 0.0441539514928,
          "menn": 0.0429003165217
        },
        {
          "alder": 12,
          "kvinner": 0.0526245847176,
          "menn": 0.0445559427953
        },
        {
          "alder": 13,
          "kvinner": 0.0699194367601,
          "menn": 0.0526277434322
        },
        {
          "alder": 14,
          "kvinner": 0.093177511055,
          "menn": 0.0656018359433
        },
        {
          "alder": 15,
          "kvinner": 0.113285787523,
          "menn": 0.0757805395574
        },
        {
          "alder": 16,
          "kvinner": 0.131429799875,
          "menn": 0.0819946660051
        },
        {
          "alder": 17,
          "kvinner": 0.144713113959,
          "menn": 0.0873709827325
        },
        {
          "alder": 18,
          "kvinner": 0.148871747271,
          "menn": 0.0871238354481
        },
        {
          "alder": 19,
          "kvinner": 0.143083471721,
          "menn": 0.0831794297425
        },
        {
          "alder": 20,
          "kvinner": 0.146381589275,
          "menn": 0.0814926577659
        },
        {
          "alder": 21,
          "kvinner": 0.146567637816,
          "menn": 0.0819117528805
        },
        {
          "alder": 22,
          "kvinner": 0.147562235906,
          "menn": 0.0844374067281
        },
        {
          "alder": 23,
          "kvinner": 0.147691416643,
          "menn": 0.0864313787406
        },
        {
          "alder": 24,
          "kvinner": 0.148630505628,
          "menn": 0.0889493256369
        },
        {
          "alder": 25,
          "kvinner": 0.151550580527,
          "menn": 0.091457960644
        },
        {
          "alder": 26,
          "kvinner": 0.153410025117,
          "menn": 0.0925347334063
        },
        {
          "alder": 27,
          "kvinner": 0.151797801858,
          "menn": 0.0958021535813
        },
        {
          "alder": 28,
          "kvinner": 0.153400868307,
          "menn": 0.0971735490781
        },
        {
          "alder": 29,
          "kvinner": 0.155469736195,
          "menn": 0.100130172826
        },
        {
          "alder": 30,
          "kvinner": 0.161901203597,
          "menn": 0.103632158749
        },
        {
          "alder": 31,
          "kvinner": 0.166460422675,
          "menn": 0.105368226199
        },
        {
          "alder": 32,
          "kvinner": 0.172017469926,
          "menn": 0.107741512649
        },
        {
          "alder": 33,
          "kvinner": 0.174868004224,
          "menn": 0.109563233031
        },
        {
          "alder": 34,
          "kvinner": 0.177409405013,
          "menn": 0.112019321079
        },
        {
          "alder": 35,
          "kvinner": 0.176397685801,
          "menn": 0.110237110738
        },
        {
          "alder": 36,
          "kvinner": 0.176807683882,
          "menn": 0.113139480471
        },
        {
          "alder": 37,
          "kvinner": 0.175663778324,
          "menn": 0.116594893543
        },
        {
          "alder": 38,
          "kvinner": 0.178060404092,
          "menn": 0.11673476103
        },
        {
          "alder": 39,
          "kvinner": 0.179630875428,
          "menn": 0.120154653959
        },
        {
          "alder": 40,
          "kvinner": 0.183645351656,
          "menn": 0.126362580415
        },
        {
          "alder": 41,
          "kvinner": 0.185311029796,
          "menn": 0.12774214473
        },
        {
          "alder": 42,
          "kvinner": 0.185758587362,
          "menn": 0.128844396863
        },
        {
          "alder": 43,
          "kvinner": 0.185570145936,
          "menn": 0.129148280743
        },
        {
          "alder": 44,
          "kvinner": 0.184515116004,
          "menn": 0.133478768479
        },
        {
          "alder": 45,
          "kvinner": 0.18632584618,
          "menn": 0.133518396688
        },
        {
          "alder": 46,
          "kvinner": 0.189068535482,
          "menn": 0.137588190828
        },
        {
          "alder": 47,
          "kvinner": 0.195320425416,
          "menn": 0.144323906468
        },
        {
          "alder": 48,
          "kvinner": 0.203415257634,
          "menn": 0.150789075449
        },
        {
          "alder": 49,
          "kvinner": 0.211078996518,
          "menn": 0.158426246316
        },
        {
          "alder": 50,
          "kvinner": 0.219524729124,
          "menn": 0.168573568532
        },
        {
          "alder": 51,
          "kvinner": 0.228621062637,
          "menn": 0.177922530269
        },
        {
          "alder": 52,
          "kvinner": 0.235539196751,
          "menn": 0.182980084193
        },
        {
          "alder": 53,
          "kvinner": 0.240651410922,
          "menn": 0.18984361684
        },
        {
          "alder": 54,
          "kvinner": 0.246506286961,
          "menn": 0.200652617564
        },
        {
          "alder": 55,
          "kvinner": 0.252355620867,
          "menn": 0.208694341476
        },
        {
          "alder": 56,
          "kvinner": 0.255656054173,
          "menn": 0.216311486704
        },
        {
          "alder": 57,
          "kvinner": 0.259184050212,
          "menn": 0.22436744713
        },
        {
          "alder": 58,
          "kvinner": 0.261609284916,
          "menn": 0.229353308968
        },
        {
          "alder": 59,
          "kvinner": 0.262396075558,
          "menn": 0.23388102331
        },
        {
          "alder": 60,
          "kvinner": 0.266441071256,
          "menn": 0.24141297206
        },
        {
          "alder": 61,
          "kvinner": 0.267716024551,
          "menn": 0.247085315572
        },
        {
          "alder": 62,
          "kvinner": 0.269840957663,
          "menn": 0.250543383619
        },
        {
          "alder": 63,
          "kvinner": 0.273014395425,
          "menn": 0.260819895136
        },
        {
          "alder": 64,
          "kvinner": 0.283791544766,
          "menn": 0.268200839649
        },
        {
          "alder": 65,
          "kvinner": 0.291574226075,
          "menn": 0.278468780629
        },
        {
          "alder": 66,
          "kvinner": 0.300271152362,
          "menn": 0.283758870801
        },
        {
          "alder": 67,
          "kvinner": 0.30463154544,
          "menn": 0.291170461179
        },
        {
          "alder": 68,
          "kvinner": 0.310545882873,
          "menn": 0.293998184875
        },
        {
          "alder": 69,
          "kvinner": 0.314278882438,
          "menn": 0.298393422839
        },
        {
          "alder": 70,
          "kvinner": 0.314482934743,
          "menn": 0.305607690547
        },
        {
          "alder": 71,
          "kvinner": 0.311980490996,
          "menn": 0.29957095282
        },
        {
          "alder": 72,
          "kvinner": 0.320013010196,
          "menn": 0.310127326151
        },
        {
          "alder": 73,
          "kvinner": 0.338745944432,
          "menn": 0.326354048934
        },
        {
          "alder": 74,
          "kvinner": 0.362322403028,
          "menn": 0.35434206525
        },
        {
          "alder": 75,
          "kvinner": 0.383809061631,
          "menn": 0.378392514122
        },
        {
          "alder": 76,
          "kvinner": 0.418076146382,
          "menn": 0.414763122535
        },
        {
          "alder": 77,
          "kvinner": 0.426713668508,
          "menn": 0.42670868718
        },
        {
          "alder": 78,
          "kvinner": 0.41850421884,
          "menn": 0.416148648649
        },
        {
          "alder": 79,
          "kvinner": 0.410414772153,
          "menn": 0.424934060664
        },
        {
          "alder": 80,
          "kvinner": 0.394923154276,
          "menn": 0.396006103629
        },
        {
          "alder": 81,
          "kvinner": 0.393827782174,
          "menn": 0.395054816046
        },
        {
          "alder": 82,
          "kvinner": 0.400624446619,
          "menn": 0.408233796156
        },
        {
          "alder": 83,
          "kvinner": 0.415633423181,
          "menn": 0.417187109668
        },
        {
          "alder": 84,
          "kvinner": 0.412860863505,
          "menn": 0.418808231801
        },
        {
          "alder": 85,
          "kvinner": 0.399761359858,
          "menn": 0.407181513616
        },
        {
          "alder": 86,
          "kvinner": 0.387224172518,
          "menn": 0.402952768624
        },
        {
          "alder": 87,
          "kvinner": 0.375584857507,
          "menn": 0.394049478694
        },
        {
          "alder": 88,
          "kvinner": 0.380486372755,
          "menn": 0.398105457289
        },
        {
          "alder": 89,
          "kvinner": 0.380693350654,
          "menn": 0.407827287066
        },
        {
          "alder": 90,
          "kvinner": 0.389302787608,
          "menn": 0.409927024908
        },
        {
          "alder": 91,
          "kvinner": 0.390003229395,
          "menn": 0.417035072207
        },
        {
          "alder": 92,
          "kvinner": 0.391428938027,
          "menn": 0.414661548544
        },
        {
          "alder": 93,
          "kvinner": 0.37722675702,
          "menn": 0.413357619915
        },
        {
          "alder": 94,
          "kvinner": 0.379206845903,
          "menn": 0.41976725127
        },
        {
          "alder": 95,
          "kvinner": 0.369970798183,
          "menn": 0.406111603189
        }
      ]
    }
  ]
}
