{
  "innhold": [
    {
      "type": "barchart",
      "data": "qwerty",
      "x": ["Snitt_rate"],
      "y": "area",
  "height": 1600,
  "barSize": 14,

  "sort": "order_index",     
  "ySort": "order_index",
      "xLabel": {
        "nn": "Tal pasientar pr. 10 000 innbyggjarar (DPS-område)",
        "en": "Number of patients pr. 10,000 population (District psychiatric center)"
      },
      "yLabel": {
        "nn": "DPS- og RHF-område",
        "en": "District psychiatric center"
      },
      "errorBars": ["lowercl", "uppercl"],
      "format": ",.1f"
    },
    {
      "type": "barchart",
      "data": "qwerty",
      "x": ["Snitt_rate"],
      "y": "area",
  "height": 1600,
  "barSize": 14,

  "sort": "order_index",     
  "ySort": "order_index",
      "xLabel": {
        "nn": "Tal pasientar pr. 10 000  innbyggjarar (DPS-område)",
        "en": "Number of patients pr. 10,000 population (District psychiatric center)"
      },
      "yLabel": {
        "nn": "DPS- og RHF-område",
        "en": "District psychiatric center"
      },
      "annualVar": [
        "Rate.2020",
        "Rate.2021",
        "Rate.2022",
        "Rate.2023",
        "Rate.2024"
      ],
      "annualVarLabels": {
        "nn": ["2020", "2021", "2022", "2023", "2024"],
        "en": ["2020", "2021", "2022", "2023", "2024"]
      }
    },

    {
      "type": "table",
      "data": "qwerty",
  "sort": "order_index",   
      "caption": {
        "nn": "Årlege gjennomsnittsverdiar for perioden 2020–2024. Pasientrate pr. 10 000 innbyggjarar DPS-område",
        "en": "Annual average during 2020–2024. Patient rate pr. 10,000 population (District psychiatric center)"
      },
      "columns": [
        {
          "id": "area",
          "label_no": "DPS- og RHF-område",
          "label_en": "District psychiatric center",
          "typeVar": "string",
          "format": ""
        },
        {
          "id": "Snitt_rate",
          "label_no": "Rate",
          "label_en": "Rate",
          "typeVar": "number",
          "format": ",.1f"
        },
        {
          "id": "Tal_pas",
          "label_no": "Tal pasientar",
          "label_en": "Number of patients",
          "typeVar": "number",
          "format": ",.0f"
        },
        {
          "id": "Innbyggarar",
          "label_no": "Innbyggjarar (18-64 år)",
          "label_en": "Population (18-64 years)",
          "typeVar": "number",
          "format": ",.0f"
        }
      ]
    },
    {
      "type": "map",
      "data": "qwerty",
      "x": "Snitt_rate",
      "caption": {
        "nn": "Tal pasientar pr. 10 000  innbyggjarar (DPS-område)",
        "en": "Number of patient pr. 10,000 population (District psychiatric center)"
      },
      "jenks": [
        {
          "grense": 514
        },
        {
          "grense": 563
        },
        {
          "grense": 616
        }
      ],
      "format": ",.1f"
    },
    {
      "type": "data",
      "label": "qwerty",
      "description": "Hoveddatasettet for gitt resultatboks",
      "national": "Noreg",
      "data":
    [
  {
    "area": "Jæren",
    "Tal_pas": 1983.6,
    "Innbyggarar": 43058.2,
    "Snitt_rate": 455.32,
    "order_index": 1,
    "lowercl": 446.38,
    "uppercl": 464.39,
    "Rate.2020": 453.37,
    "Rate.2021": 475.87,
    "Rate.2022": 463.85,
    "Rate.2023": 440.18,
    "Rate.2024": 443.33
  },
  {
    "area": "Sola",
    "Tal_pas": 2648,
    "Innbyggarar": 56626.4,
    "Snitt_rate": 466.84,
    "order_index": 2,
    "lowercl": 458.91,
    "uppercl": 474.87,
    "Rate.2020": 446.9,
    "Rate.2021": 470.37,
    "Rate.2022": 484.9,
    "Rate.2023": 480.65,
    "Rate.2024": 451.39
  },
  {
    "area": "Sandnes",
    "Tal_pas": 2831.6,
    "Innbyggarar": 59837.4,
    "Snitt_rate": 470.7,
    "order_index": 3,
    "lowercl": 462.96,
    "uppercl": 478.54,
    "Rate.2020": 446,
    "Rate.2021": 482.35,
    "Rate.2022": 483.3,
    "Rate.2023": 475.83,
    "Rate.2024": 466.03
  },
  {
    "area": "Stavanger",
    "Tal_pas": 3028.4,
    "Innbyggarar": 60048.4,
    "Snitt_rate": 495.24,
    "order_index": 4,
    "lowercl": 487.37,
    "uppercl": 503.2,
    "Rate.2020": 492.42,
    "Rate.2021": 524.81,
    "Rate.2022": 513.88,
    "Rate.2023": 498.95,
    "Rate.2024": 446.13
  },
  {
    "area": "Haugaland",
    "Tal_pas": 2328.6,
    "Innbyggarar": 46008.8,
    "Snitt_rate": 513.87,
    "order_index": 5,
    "lowercl": 504.55,
    "uppercl": 523.32,
    "Rate.2020": 505.93,
    "Rate.2021": 540.36,
    "Rate.2022": 547.62,
    "Rate.2023": 501.38,
    "Rate.2024": 474.06
  },
  {
    "area": "Helse Vest",
    "Tal_pas": 37439.2,
    "Innbyggarar": 690956,
    "Snitt_rate": 538.33,
    "order_index": 6,
    "lowercl": 535.89,
    "uppercl": 540.77,
    "Rate.2020": 524.99,
    "Rate.2021": 549.26,
    "Rate.2022": 570.24,
    "Rate.2023": 537.93,
    "Rate.2024": 509.23
  },
  {
    "area": "Karmøy",
    "Tal_pas": 1350,
    "Innbyggarar": 25239,
    "Snitt_rate": 538.69,
    "order_index": 7,
    "lowercl": 525.89,
    "uppercl": 551.72,
    "Rate.2020": 518.52,
    "Rate.2021": 552.55,
    "Rate.2022": 612.79,
    "Rate.2023": 526.35,
    "Rate.2024": 483.24
  },
  {
    "area": "Førde",
    "Tal_pas": 1138,
    "Innbyggarar": 21661.4,
    "Snitt_rate": 539.57,
    "order_index": 8,
    "lowercl": 525.56,
    "uppercl": 553.86,
    "Rate.2020": 562.66,
    "Rate.2021": 511.78,
    "Rate.2022": 560.88,
    "Rate.2023": 537.98,
    "Rate.2024": 524.55
  },
  {
    "area": "Indre Sogn",
    "Tal_pas": 912.4,
    "Innbyggarar": 16959.6,
    "Snitt_rate": 546.3,
    "order_index": 9,
    "lowercl": 530.52,
    "uppercl": 562.43,
    "Rate.2020": 523.94,
    "Rate.2021": 562.26,
    "Rate.2022": 615.18,
    "Rate.2023": 549.66,
    "Rate.2024": 480.46
  },
  {
    "area": "Dalane",
    "Tal_pas": 757,
    "Innbyggarar": 14157.2,
    "Snitt_rate": 547.48,
    "order_index": 10,
    "lowercl": 530.12,
    "uppercl": 565.26,
    "Rate.2020": 567.65,
    "Rate.2021": 588.39,
    "Rate.2022": 594.43,
    "Rate.2023": 521.15,
    "Rate.2024": 465.77
  },
  {
    "area": "Bjørgvin",
    "Tal_pas": 3263,
    "Innbyggarar": 59842,
    "Snitt_rate": 553.1,
    "order_index": 11,
    "lowercl": 544.64,
    "uppercl": 561.67,
    "Rate.2020": 521.69,
    "Rate.2021": 562.42,
    "Rate.2022": 583.33,
    "Rate.2023": 555.31,
    "Rate.2024": 542.77
  },
  {
    "area": "Stord",
    "Tal_pas": 1189.6,
    "Innbyggarar": 21554.6,
    "Snitt_rate": 559.79,
    "order_index": 12,
    "lowercl": 545.61,
    "uppercl": 574.24,
    "Rate.2020": 534.77,
    "Rate.2021": 574.91,
    "Rate.2022": 605.58,
    "Rate.2023": 572.7,
    "Rate.2024": 510.98
  },
  {
    "area": "Betanien",
    "Tal_pas": 2568.6,
    "Innbyggarar": 44299,
    "Snitt_rate": 574.43,
    "order_index": 13,
    "lowercl": 564.52,
    "uppercl": 584.46,
    "Rate.2020": 565.28,
    "Rate.2021": 579.46,
    "Rate.2022": 610.08,
    "Rate.2023": 565.78,
    "Rate.2024": 551.54
  },
  {
    "area": "Folgefonn",
    "Tal_pas": 795.4,
    "Innbyggarar": 13640.4,
    "Snitt_rate": 609.75,
    "order_index": 14,
    "lowercl": 590.75,
    "uppercl": 629.22,
    "Rate.2020": 585.72,
    "Rate.2021": 615.61,
    "Rate.2022": 645.03,
    "Rate.2023": 612.2,
    "Rate.2024": 590.21
  },
  {
    "area": "Nordfjord",
    "Tal_pas": 1365,
    "Innbyggarar": 22975.8,
    "Snitt_rate": 610.17,
    "order_index": 15,
    "lowercl": 595.69,
    "uppercl": 624.91,
    "Rate.2020": 578.68,
    "Rate.2021": 619.67,
    "Rate.2022": 644.31,
    "Rate.2023": 635.48,
    "Rate.2024": 572.71
  },
  {
    "area": "Øyane",
    "Tal_pas": 2635.8,
    "Innbyggarar": 41197.4,
    "Snitt_rate": 645.67,
    "order_index": 16,
    "lowercl": 634.65,
    "uppercl": 656.83,
    "Rate.2020": 587.03,
    "Rate.2021": 606.46,
    "Rate.2022": 691.7,
    "Rate.2023": 659.12,
    "Rate.2024": 684.03
  },
  {
    "area": "Solli",
    "Tal_pas": 2928.2,
    "Innbyggarar": 45902.6,
    "Snitt_rate": 647.42,
    "order_index": 17,
    "lowercl": 636.94,
    "uppercl": 658.03,
    "Rate.2020": 608.24,
    "Rate.2021": 651.24,
    "Rate.2022": 680.3,
    "Rate.2023": 656.39,
    "Rate.2024": 640.96
  },
  {
    "area": "Kronstad",
    "Tal_pas": 5635.6,
    "Innbyggarar": 80855.8,
    "Snitt_rate": 653.05,
    "order_index": 18,
    "lowercl": 645.19,
    "uppercl": 660.99,
    "Rate.2020": 680.83,
    "Rate.2021": 676.75,
    "Rate.2022": 693.42,
    "Rate.2023": 633.38,
    "Rate.2024": 580.89
  },
  {
    "area": "Voss",
    "Tal_pas": 1182,
    "Innbyggarar": 17092,
    "Snitt_rate": 708.97,
    "order_index": 19,
    "lowercl": 690.95,
    "uppercl": 727.34,
    "Rate.2020": 735.03,
    "Rate.2021": 746.65,
    "Rate.2022": 777.51,
    "Rate.2023": 696.48,
    "Rate.2024": 589.18
  },
  {
    "area": "Strømme",
    "Tal_pas": 1066.2,
    "Innbyggarar": 23357.4,
    "Snitt_rate": 463.55,
    "order_index": 20,
    "lowercl": 451.17,
    "uppercl": 476.18,
    "Rate.2020": 425.06,
    "Rate.2021": 452.51,
    "Rate.2022": 491.2,
    "Rate.2023": 480.61,
    "Rate.2024": 468.39
  },
  {
    "area": "Lister",
    "Tal_pas": 1054,
    "Innbyggarar": 22448,
    "Snitt_rate": 480.01,
    "order_index": 21,
    "lowercl": 467.08,
    "uppercl": 493.2,
    "Rate.2020": 513.83,
    "Rate.2021": 442.33,
    "Rate.2022": 491.04,
    "Rate.2023": 498.96,
    "Rate.2024": 453.87
  },
  {
    "area": "Nedre Romerike",
    "Tal_pas": 5445.6,
    "Innbyggarar": 113882.8,
    "Snitt_rate": 483.59,
    "order_index": 22,
    "lowercl": 477.84,
    "uppercl": 489.39,
    "Rate.2020": 448.99,
    "Rate.2021": 484.44,
    "Rate.2022": 497.94,
    "Rate.2023": 500.92,
    "Rate.2024": 485.65
  },
  {
    "area": "Bærum",
    "Tal_pas": 3629.4,
    "Innbyggarar": 77044.6,
    "Snitt_rate": 487.65,
    "order_index": 23,
    "lowercl": 480.51,
    "uppercl": 494.88,
    "Rate.2020": 487.65,
    "Rate.2021": 485.04,
    "Rate.2022": 496.09,
    "Rate.2023": 489.88,
    "Rate.2024": 479.61
  },
  {
    "area": "Øvre Romerike",
    "Tal_pas": 3545.8,
    "Innbyggarar": 73207,
    "Snitt_rate": 489.44,
    "order_index": 24,
    "lowercl": 482.24,
    "uppercl": 496.73,
    "Rate.2020": 458.46,
    "Rate.2021": 506.36,
    "Rate.2022": 504.38,
    "Rate.2023": 496.03,
    "Rate.2024": 481.98
  },
  {
    "area": "Tynset",
    "Tal_pas": 501.2,
    "Innbyggarar": 10388.2,
    "Snitt_rate": 510.81,
    "order_index": 25,
    "lowercl": 490.67,
    "uppercl": 531.56,
    "Rate.2020": 484.98,
    "Rate.2021": 509.1,
    "Rate.2022": 544.47,
    "Rate.2023": 528.8,
    "Rate.2024": 486.7
  },
  {
    "area": "Gjøvik",
    "Tal_pas": 3267.2,
    "Innbyggarar": 66054.6,
    "Snitt_rate": 515.72,
    "order_index": 26,
    "lowercl": 507.78,
    "uppercl": 523.74,
    "Rate.2020": 529.2,
    "Rate.2021": 552.39,
    "Rate.2022": 526.45,
    "Rate.2023": 499.41,
    "Rate.2024": 471.12
  },
  {
    "area": "Nordre Østfold",
    "Tal_pas": 4104.2,
    "Innbyggarar": 80008,
    "Snitt_rate": 530.62,
    "order_index": 27,
    "lowercl": 523.34,
    "uppercl": 537.97,
    "Rate.2020": 530.16,
    "Rate.2021": 556.98,
    "Rate.2022": 550.27,
    "Rate.2023": 542.87,
    "Rate.2024": 472.81
  },
  {
    "area": "Vindern",
    "Tal_pas": 5271,
    "Innbyggarar": 94447.6,
    "Snitt_rate": 531.95,
    "order_index": 28,
    "lowercl": 525.45,
    "uppercl": 538.51,
    "Rate.2020": 541.95,
    "Rate.2021": 539.13,
    "Rate.2022": 527.15,
    "Rate.2023": 522.69,
    "Rate.2024": 528.83
  },
  {
    "area": "Follo",
    "Tal_pas": 3755.8,
    "Innbyggarar": 71311.6,
    "Snitt_rate": 538.91,
    "order_index": 29,
    "lowercl": 531.17,
    "uppercl": 546.74,
    "Rate.2020": 501.79,
    "Rate.2021": 540.24,
    "Rate.2022": 538.7,
    "Rate.2023": 558.93,
    "Rate.2024": 554.9
  },
  {
    "area": "Lillehammer",
    "Tal_pas": 2174.4,
    "Innbyggarar": 41376,
    "Snitt_rate": 540.28,
    "order_index": 30,
    "lowercl": 530.1,
    "uppercl": 550.62,
    "Rate.2020": 526.32,
    "Rate.2021": 520.2,
    "Rate.2022": 554.59,
    "Rate.2023": 577.95,
    "Rate.2024": 522.36
  },
  {
    "area": "Asker",
    "Tal_pas": 3034.8,
    "Innbyggarar": 57791,
    "Snitt_rate": 544.77,
    "order_index": 31,
    "lowercl": 536.01,
    "uppercl": 553.64,
    "Rate.2020": 513.57,
    "Rate.2021": 547.43,
    "Rate.2022": 571.48,
    "Rate.2023": 557.58,
    "Rate.2024": 533.8
  },
  {
    "area": "Helse Sør-Øst",
    "Tal_pas": 105818.4,
    "Innbyggarar": 1911214.4,
    "Snitt_rate": 553.15,
    "order_index": 32,
    "lowercl": 551.66,
    "uppercl": 554.64,
    "Rate.2020": 535.78,
    "Rate.2021": 553.46,
    "Rate.2022": 566.03,
    "Rate.2023": 567.22,
    "Rate.2024": 543.24
  },
  {
    "area": "Solvang",
    "Tal_pas": 4006.4,
    "Innbyggarar": 70965,
    "Snitt_rate": 554.89,
    "order_index": 33,
    "lowercl": 547.21,
    "uppercl": 562.66,
    "Rate.2020": 531.46,
    "Rate.2021": 559.33,
    "Rate.2022": 581.67,
    "Rate.2023": 570.73,
    "Rate.2024": 531.28
  },
  {
    "area": "Drammen",
    "Tal_pas": 4417.8,
    "Innbyggarar": 80078.2,
    "Snitt_rate": 557.31,
    "order_index": 34,
    "lowercl": 549.97,
    "uppercl": 564.73,
    "Rate.2020": 536.28,
    "Rate.2021": 555.97,
    "Rate.2022": 568.69,
    "Rate.2023": 567.03,
    "Rate.2024": 558.6
  },
  {
    "area": "Halden Sarpsborg",
    "Tal_pas": 3325.8,
    "Innbyggarar": 60827.2,
    "Snitt_rate": 558.84,
    "order_index": 35,
    "lowercl": 550.36,
    "uppercl": 567.42,
    "Rate.2020": 536.84,
    "Rate.2021": 566.69,
    "Rate.2022": 573.29,
    "Rate.2023": 564.44,
    "Rate.2024": 552.97
  },
  {
    "area": "Øvre Telemark",
    "Tal_pas": 1457.8,
    "Innbyggarar": 26106,
    "Snitt_rate": 578.63,
    "order_index": 36,
    "lowercl": 565.34,
    "uppercl": 592.15,
    "Rate.2020": 607.2,
    "Rate.2021": 555.69,
    "Rate.2022": 589.25,
    "Rate.2023": 596.13,
    "Rate.2024": 544.87
  },
  {
    "area": "Søndre Oslo",
    "Tal_pas": 5137,
    "Innbyggarar": 88694.4,
    "Snitt_rate": 578.73,
    "order_index": 37,
    "lowercl": 571.63,
    "uppercl": 585.89,
    "Rate.2020": 553.42,
    "Rate.2021": 567.74,
    "Rate.2022": 578.2,
    "Rate.2023": 599.04,
    "Rate.2024": 595.24
  },
  {
    "area": "Østre Agder",
    "Tal_pas": 4030.6,
    "Innbyggarar": 71222,
    "Snitt_rate": 581.64,
    "order_index": 38,
    "lowercl": 573.61,
    "uppercl": 589.76,
    "Rate.2020": 586.95,
    "Rate.2021": 595.21,
    "Rate.2022": 610.46,
    "Rate.2023": 570.55,
    "Rate.2024": 545.04
  },
  {
    "area": "Elverum - Hamar",
    "Tal_pas": 4698.2,
    "Innbyggarar": 82229.6,
    "Snitt_rate": 587.54,
    "order_index": 39,
    "lowercl": 580.03,
    "uppercl": 595.13,
    "Rate.2020": 538.21,
    "Rate.2021": 597.05,
    "Rate.2022": 616.68,
    "Rate.2023": 608.83,
    "Rate.2024": 576.93
  },
  {
    "area": "Fredrikstad",
    "Tal_pas": 3050,
    "Innbyggarar": 53299.2,
    "Snitt_rate": 589,
    "order_index": 40,
    "lowercl": 579.65,
    "uppercl": 598.46,
    "Rate.2020": 566.82,
    "Rate.2021": 572.3,
    "Rate.2022": 600.48,
    "Rate.2023": 624.53,
    "Rate.2024": 580.87
  },
  {
    "area": "Groruddalen",
    "Tal_pas": 5126.2,
    "Innbyggarar": 86059.6,
    "Snitt_rate": 591.54,
    "order_index": 41,
    "lowercl": 584.31,
    "uppercl": 598.85,
    "Rate.2020": 546.43,
    "Rate.2021": 575.18,
    "Rate.2022": 591.39,
    "Rate.2023": 626.2,
    "Rate.2024": 618.53
  },
  {
    "area": "Nydalen",
    "Tal_pas": 6203.4,
    "Innbyggarar": 95950.6,
    "Snitt_rate": 601.48,
    "order_index": 42,
    "lowercl": 594.55,
    "uppercl": 608.47,
    "Rate.2020": 593.12,
    "Rate.2021": 604.39,
    "Rate.2022": 616.95,
    "Rate.2023": 605.95,
    "Rate.2024": 586.99
  },
  {
    "area": "Vestfold",
    "Tal_pas": 8935,
    "Innbyggarar": 149498,
    "Snitt_rate": 616.22,
    "order_index": 43,
    "lowercl": 610.5,
    "uppercl": 621.99,
    "Rate.2020": 593.62,
    "Rate.2021": 593.87,
    "Rate.2022": 631.55,
    "Rate.2023": 651.9,
    "Rate.2024": 610.17
  },
  {
    "area": "Nedre Telemark",
    "Tal_pas": 4999.6,
    "Innbyggarar": 76887.2,
    "Snitt_rate": 669.07,
    "order_index": 44,
    "lowercl": 660.77,
    "uppercl": 677.45,
    "Rate.2020": 652.63,
    "Rate.2021": 652.3,
    "Rate.2022": 691.34,
    "Rate.2023": 688.73,
    "Rate.2024": 660.36
  },
  {
    "area": "Kongsvinger",
    "Tal_pas": 1496.2,
    "Innbyggarar": 24071.8,
    "Snitt_rate": 671.81,
    "order_index": 45,
    "lowercl": 656.47,
    "uppercl": 687.42,
    "Rate.2020": 746.56,
    "Rate.2021": 745.96,
    "Rate.2022": 676.08,
    "Rate.2023": 614.86,
    "Rate.2024": 575.58
  },
  {
    "area": "Ringerike",
    "Tal_pas": 3169.4,
    "Innbyggarar": 48841,
    "Snitt_rate": 674.03,
    "order_index": 46,
    "lowercl": 663.52,
    "uppercl": 684.66,
    "Rate.2020": 666.96,
    "Rate.2021": 671.95,
    "Rate.2022": 663.59,
    "Rate.2023": 697.27,
    "Rate.2024": 670.37
  },
  {
    "area": "Kongsberg",
    "Tal_pas": 2324.6,
    "Innbyggarar": 34847.8,
    "Snitt_rate": 686.82,
    "order_index": 47,
    "lowercl": 674.35,
    "uppercl": 699.46,
    "Rate.2020": 645.27,
    "Rate.2021": 686.93,
    "Rate.2022": 702.87,
    "Rate.2023": 721.75,
    "Rate.2024": 677.28
  },
  {
    "area": "Lovisenberg",
    "Tal_pas": 10275.6,
    "Innbyggarar": 130320,
    "Snitt_rate": 734.02,
    "order_index": 48,
    "lowercl": 726.9,
    "uppercl": 741.2,
    "Rate.2020": 714.07,
    "Rate.2021": 742.44,
    "Rate.2022": 738.75,
    "Rate.2023": 752.06,
    "Rate.2024": 722.78
  },
  {
    "area": "Sunnmøre",
    "Tal_pas": 2753.2,
    "Innbyggarar": 59903.6,
    "Snitt_rate": 462.56,
    "order_index": 49,
    "lowercl": 454.85,
    "uppercl": 470.36,
    "Rate.2020": 430.26,
    "Rate.2021": 451.33,
    "Rate.2022": 480.13,
    "Rate.2023": 479.01,
    "Rate.2024": 472.05
  },
  {
    "area": "Levanger",
    "Tal_pas": 1869.6,
    "Innbyggarar": 39318.2,
    "Snitt_rate": 485.54,
    "order_index": 50,
    "lowercl": 475.71,
    "uppercl": 495.53,
    "Rate.2020": 454.76,
    "Rate.2021": 471.27,
    "Rate.2022": 550.81,
    "Rate.2023": 484.27,
    "Rate.2024": 466.59
  },
  {
    "area": "Namsos",
    "Tal_pas": 1111.8,
    "Innbyggarar": 21429.8,
    "Snitt_rate": 531.93,
    "order_index": 51,
    "lowercl": 517.96,
    "uppercl": 546.18,
    "Rate.2020": 550.67,
    "Rate.2021": 551.22,
    "Rate.2022": 542.45,
    "Rate.2023": 512.33,
    "Rate.2024": 502.96
  },
  {
    "area": "Volda",
    "Tal_pas": 1543.6,
    "Innbyggarar": 29141,
    "Snitt_rate": 540.57,
    "order_index": 52,
    "lowercl": 528.51,
    "uppercl": 552.83,
    "Rate.2020": 590.64,
    "Rate.2021": 564.3,
    "Rate.2022": 565.73,
    "Rate.2023": 516.79,
    "Rate.2024": 465.39
  },
  {
    "area": "Helse Midt",
    "Tal_pas": 24945.6,
    "Innbyggarar": 448620.4,
    "Snitt_rate": 554.64,
    "order_index": 53,
    "lowercl": 551.56,
    "uppercl": 557.73,
    "Rate.2020": 545.92,
    "Rate.2021": 567.65,
    "Rate.2022": 582.7,
    "Rate.2023": 544.31,
    "Rate.2024": 532.63
  },
  {
    "area": "Molde",
    "Tal_pas": 2291.8,
    "Innbyggarar": 42297.6,
    "Snitt_rate": 557.06,
    "order_index": 54,
    "lowercl": 546.88,
    "uppercl": 567.39,
    "Rate.2020": 550.42,
    "Rate.2021": 567.62,
    "Rate.2022": 587.93,
    "Rate.2023": 529.71,
    "Rate.2024": 549.64
  },
  {
    "area": "Stjørdal",
    "Tal_pas": 1091.8,
    "Innbyggarar": 19977.6,
    "Snitt_rate": 563.44,
    "order_index": 55,
    "lowercl": 548.51,
    "uppercl": 578.67,
    "Rate.2020": 561.98,
    "Rate.2021": 557.76,
    "Rate.2022": 606.76,
    "Rate.2023": 560.98,
    "Rate.2024": 529.71
  },
  {
    "area": "Nidaros",
    "Tal_pas": 6243,
    "Innbyggarar": 98874,
    "Snitt_rate": 602.52,
    "order_index": 56,
    "lowercl": 595.8,
    "uppercl": 609.3,
    "Rate.2020": 603.98,
    "Rate.2021": 630.07,
    "Rate.2022": 634.34,
    "Rate.2023": 576.66,
    "Rate.2024": 567.55
  },
  {
    "area": "Nidelv",
    "Tal_pas": 6841.2,
    "Innbyggarar": 111743,
    "Snitt_rate": 603.65,
    "order_index": 57,
    "lowercl": 597.26,
    "uppercl": 610.09,
    "Rate.2020": 585.02,
    "Rate.2021": 620.97,
    "Rate.2022": 623.16,
    "Rate.2023": 601.33,
    "Rate.2024": 587.79
  },
  {
    "area": "Kristiansund",
    "Tal_pas": 1774.4,
    "Innbyggarar": 25935.6,
    "Snitt_rate": 713.19,
    "order_index": 58,
    "lowercl": 698.36,
    "uppercl": 728.25,
    "Rate.2020": 697.9,
    "Rate.2021": 764.32,
    "Rate.2022": 742.63,
    "Rate.2023": 689.19,
    "Rate.2024": 671.9
  },
  {
    "area": "Tromsø og omegn",
    "Tal_pas": 2904,
    "Innbyggarar": 57938.4,
    "Snitt_rate": 488.78,
    "order_index": 59,
    "lowercl": 480.84,
    "uppercl": 496.83,
    "Rate.2020": 389.51,
    "Rate.2021": 468.67,
    "Rate.2022": 500.02,
    "Rate.2023": 528.88,
    "Rate.2024": 556.85
  },
  {
    "area": "Mosjøen",
    "Tal_pas": 464.4,
    "Innbyggarar": 9392.6,
    "Snitt_rate": 510.01,
    "order_index": 60,
    "lowercl": 489.35,
    "uppercl": 531.31,
    "Rate.2020": 517.47,
    "Rate.2021": 458.63,
    "Rate.2022": 492,
    "Rate.2023": 564.42,
    "Rate.2024": 517.51
  },
  {
    "area": "Mo i Rana",
    "Tal_pas": 1026.2,
    "Innbyggarar": 19807,
    "Snitt_rate": 532.55,
    "order_index": 61,
    "lowercl": 518.03,
    "uppercl": 547.38,
    "Rate.2020": 548.75,
    "Rate.2021": 550.47,
    "Rate.2022": 532.51,
    "Rate.2023": 534.59,
    "Rate.2024": 496.42
  },
  {
    "area": "Midt-Troms",
    "Tal_pas": 1044.2,
    "Innbyggarar": 19938,
    "Snitt_rate": 539.66,
    "order_index": 62,
    "lowercl": 525.02,
    "uppercl": 554.6,
    "Rate.2020": 479.14,
    "Rate.2021": 497.58,
    "Rate.2022": 563.53,
    "Rate.2023": 601.29,
    "Rate.2024": 556.77
  },
  {
    "area": "Ofoten",
    "Tal_pas": 884.8,
    "Innbyggarar": 16832,
    "Snitt_rate": 550.62,
    "order_index": 63,
    "lowercl": 534.44,
    "uppercl": 567.17,
    "Rate.2020": 533.7,
    "Rate.2021": 547.76,
    "Rate.2022": 538.66,
    "Rate.2023": 570.59,
    "Rate.2024": 562.4
  },
  {
    "area": "Helse Nord",
    "Tal_pas": 16228.8,
    "Innbyggarar": 292185.2,
    "Snitt_rate": 563.38,
    "order_index": 64,
    "lowercl": 559.5,
    "uppercl": 567.28,
    "Rate.2020": 506.22,
    "Rate.2021": 547.27,
    "Rate.2022": 573.24,
    "Rate.2023": 597.99,
    "Rate.2024": 592.18
  },
  {
    "area": "Salten",
    "Tal_pas": 2885.6,
    "Innbyggarar": 50898,
    "Snitt_rate": 571.16,
    "order_index": 65,
    "lowercl": 561.87,
    "uppercl": 580.56,
    "Rate.2020": 508.71,
    "Rate.2021": 554.75,
    "Rate.2022": 573.12,
    "Rate.2023": 601.61,
    "Rate.2024": 617.59
  },
  {
    "area": "Lofoten",
    "Tal_pas": 800.8,
    "Innbyggarar": 14275.6,
    "Snitt_rate": 571.25,
    "order_index": 66,
    "lowercl": 553.67,
    "uppercl": 589.24,
    "Rate.2020": 465.68,
    "Rate.2021": 572.34,
    "Rate.2022": 609.23,
    "Rate.2023": 621.98,
    "Rate.2024": 587.01
  },
  {
    "area": "Vesterålen",
    "Tal_pas": 981.8,
    "Innbyggarar": 17620.6,
    "Snitt_rate": 578.55,
    "order_index": 67,
    "lowercl": 562.41,
    "uppercl": 595.04,
    "Rate.2020": 510.93,
    "Rate.2021": 528.32,
    "Rate.2022": 618.98,
    "Rate.2023": 618.19,
    "Rate.2024": 616.34
  },
  {
    "area": "Ytre Helgeland",
    "Tal_pas": 908.6,
    "Innbyggarar": 16113,
    "Snitt_rate": 591.19,
    "order_index": 68,
    "lowercl": 574.01,
    "uppercl": 608.75,
    "Rate.2020": 587.76,
    "Rate.2021": 584.59,
    "Rate.2022": 605.23,
    "Rate.2023": 631.68,
    "Rate.2024": 546.68
  },
  {
    "area": "Øst-Finnmark",
    "Tal_pas": 869.8,
    "Innbyggarar": 15071.6,
    "Snitt_rate": 597.73,
    "order_index": 69,
    "lowercl": 579.99,
    "uppercl": 615.88,
    "Rate.2020": 526.35,
    "Rate.2021": 577.17,
    "Rate.2022": 601.94,
    "Rate.2023": 620.87,
    "Rate.2024": 662.33
  },
  {
    "area": "Sør-Troms",
    "Tal_pas": 1079.8,
    "Innbyggarar": 17044.2,
    "Snitt_rate": 646.49,
    "order_index": 70,
    "lowercl": 629.33,
    "uppercl": 664,
    "Rate.2020": 610.15,
    "Rate.2021": 630.83,
    "Rate.2022": 660.12,
    "Rate.2023": 668.17,
    "Rate.2024": 663.16
  },
  {
    "area": "Midt-Finnmark",
    "Tal_pas": 432.4,
    "Innbyggarar": 7118.4,
    "Snitt_rate": 647.37,
    "order_index": 71,
    "lowercl": 620.16,
    "uppercl": 675.46,
    "Rate.2020": 549.11,
    "Rate.2021": 617.67,
    "Rate.2022": 643.61,
    "Rate.2023": 712.42,
    "Rate.2024": 714.03
  },
  {
    "area": "Vest-Finnmark",
    "Tal_pas": 1658.8,
    "Innbyggarar": 23926.4,
    "Snitt_rate": 694.5,
    "order_index": 72,
    "lowercl": 679.56,
    "uppercl": 709.67,
    "Rate.2020": 640.16,
    "Rate.2021": 701.78,
    "Rate.2022": 714.17,
    "Rate.2023": 725.13,
    "Rate.2024": 691.24
  },
  {
    "area": "Nord-Troms",
    "Tal_pas": 467.2,
    "Innbyggarar": 6209.4,
    "Snitt_rate": 787.89,
    "order_index": 73,
    "lowercl": 756.1,
    "uppercl": 820.69,
    "Rate.2020": 732.04,
    "Rate.2021": 749.6,
    "Rate.2022": 776.4,
    "Rate.2023": 817.31,
    "Rate.2024": 864.13
  },
  {
    "area": "Noreg",
    "Tal_pas": 183144.8,
    "Innbyggarar": 3342976,
    "Snitt_rate": 547.42,
    "order_index": 74,
    "lowercl": 546.3,
    "uppercl": 548.54,
    "Rate.2020": 528.8,
    "Rate.2021": 549.9,
    "Rate.2022": 565.68,
    "Rate.2023": 557.11,
    "Rate.2024": 535.59
  }
      ]
    }
  ]
}
